<alert_registratie app="zib2020-nl" shortName="alert_registratie" formName="alert" transactionRef="2.16.840.1.113883.2.4.3.11.60.121.4.2.8.3" transactionEffectiveDate="2020-09-01T00:00:00" versionDate="" prefix="zib2017-" language="nl-NL" title="bgz-msz-patA-alert1" desc="" id="4c55f95b-5a83-4692-95f9-5b5a836692ba">
    <alert conceptId="2.16.840.1.113883.2.4.3.11.60.40.1.8.3.1">
        <onderwerp conceptId="2.16.840.1.113883.2.4.3.11.999.121.1.1">
            <patient-id value="999999151" root="2.16.840.1.113883.2.4.6.3" conceptId="2.16.840.1.113883.2.4.3.11.999.121.1.2"/>
        </onderwerp>
        <alert_naam originalText="agressieve patiënt" conceptId="2.16.840.1.113883.2.4.3.11.60.40.1.8.3.4" value="12" code="OTH" codeSystem="2.16.840.1.113883.5.1008" displayName="Anders"/>
        <begin_datum_tijd value="2016" datatype="datetime" conceptId="2.16.840.1.113883.2.4.3.11.60.40.1.8.3.5"/>
        <alert_type conceptId="2.16.840.1.113883.2.4.3.11.60.40.1.8.3.6" value="2" code="74018-3" codeSystem="2.16.840.1.113883.6.1" displayName="Alert"/>
    </alert>
</alert_registratie>