<Medication xmlns="http://hl7.org/fhir">
   <id value="spenseToFHIRConversion-Product-13650203-2-16-840-1-113883-2-4-4-8"/>
   <meta>
      <profile value="http://nictiz.nl/fhir/StructureDefinition/mp612-DispenseToFHIRConversion-Product"/>
   </meta>
   <text>
      <status value="extensions"/>
      <div xmlns="http://www.w3.org/1999/xhtml">
         <table>
            <tbody>
               <tr>
                  <th>Code</th>
                  <td>
                     <span title="RESONIUM A POEDER (13650203 - G-Standaard ZI_nummer)">RESONIUM A POEDER</span>
                  </td>
               </tr>
            </tbody>
         </table>
      </div>
   </text>
   <code>
      <coding>
         <system value="urn:oid:2.16.840.1.113883.2.4.4.8"/>
         <code value="13650203"/>
         <display value="RESONIUM A POEDER"/>
         <userSelected value="true"/>
      </coding>
      <coding>
         <system value="urn:oid:2.16.840.1.113883.2.4.4.7"/>
         <code value="15261"/>
      </coding>
      <coding>
         <system value="urn:oid:2.16.840.1.113883.2.4.4.1"/>
         <code value="121363"/>
      </coding>
      <text value="RESONIUM A POEDER"/>
   </code>
</Medication>
