<Medication xmlns="http://hl7.org/fhir">
   <id value="spenseToFHIRConversion-Product-13878956-2-16-840-1-113883-2-4-4-8"/>
   <meta>
      <profile value="http://nictiz.nl/fhir/StructureDefinition/mp612-DispenseToFHIRConversion-Product"/>
   </meta>
   <text>
      <status value="extensions"/>
      <div xmlns="http://www.w3.org/1999/xhtml">
         <table>
            <tbody>
               <tr>
                  <th>Code</th>
                  <td>
                     <span title="DUROGESIC 100 MATRIXPLEISTER 16,8MG (13878956 - G-Standaard ZI_nummer)">DUROGESIC 100 MATRIXPLEISTER 16,8MG</span>
                  </td>
               </tr>
            </tbody>
         </table>
      </div>
   </text>
   <code>
      <coding>
         <system value="urn:oid:2.16.840.1.113883.2.4.4.8"/>
         <code value="13878956"/>
         <display value="DUROGESIC 100 MATRIXPLEISTER 16,8MG"/>
         <userSelected value="true"/>
      </coding>
      <coding>
         <system value="urn:oid:2.16.840.1.113883.2.4.4.7"/>
         <code value="836982"/>
      </coding>
      <coding>
         <system value="urn:oid:2.16.840.1.113883.2.4.4.1"/>
         <code value="122033"/>
      </coding>
      <text value="DUROGESIC 100 MATRIXPLEISTER 16,8MG"/>
   </code>
</Medication>
