<?xml version="1.0" encoding="UTF-8"?>
<!--Generated from HL7v3 QUMA_IN991203NL02 instance with: <id extension="OMNIHIS-20190305-1614-329e88c9-d231-416e-bdcf-7b3dcc0788ba" root="2.16.840.1.113883.2.4.6.6.90000258.1"/>-->
<adaxml xmlns:xsi="http://www.w3.org/2001/XMLSchema-instance"
        xsi:noNamespaceSchemaLocation="../ada_schemas/ada_beschikbaarstellen_medicatieafspraken.xsd">
   <meta status="new"
         created-by="generated"
         last-update-by="generated"
         creation-date="2020-06-30T14:30:04.69+02:00"
         last-update-date="2020-06-30T14:30:04.69+02:00"/>
   <data>
      <beschikbaarstellen_medicatieafspraken app="ketenzorg3.0"
                                             shortName="beschikbaarstellen_medicatieafspraken"
                                             formName="beschikbaarstellen_medicatieafspraken"
                                             transactionRef="2.16.840.1.113883.2.4.3.11.60.66.4.523"
                                             transactionEffectiveDate="2018-04-13T00:00:00"
                                             versionDate=""
                                             prefix="kz-"
                                             language="nl-NL"
                                             title="Generated Through Conversion"
                                             id="6cef3c7b-bacd-11ea-1244-020000000000">
         <patient>
            <naamgegevens>
               <initialen value="E."/>
               <naamgebruik code="NL1"
                            codeSystem="2.16.840.1.113883.2.4.3.11.60.101.5.4"
                            displayName="Eigen geslachtsnaam"/>
               <geslachtsnaam>
                  <achternaam value="XXX_Zegers"/>
               </geslachtsnaam>
            </naamgegevens>
            <adresgegevens>
               <straat value="Knolweg"/>
               <huisnummer value="1001"/>
               <postcode value="9999 XX"/>
               <woonplaats value="STITSWERD"/>
               <land value="Nederland"/>
               <adres_soort code="HP"
                            codeSystem="2.16.840.1.113883.5.1119"
                            displayName="Primary Home"/>
            </adresgegevens>
            <contactgegevens>
               <telefoonnummers>
                  <telefoonnummer value="tel:+31190531770"/>
                  <telecom_type code="UNK"
                                codeSystem="2.16.840.1.113883.5.1008"
                                displayName="unknown"/>
                  <nummer_soort code="HP"
                                codeSystem="2.16.840.1.113883.5.1119"
                                displayName="Primary Home"/>
               </telefoonnummers>
            </contactgegevens>
            <identificatienummer value="999911624" root="2.16.840.1.113883.2.4.6.3"/>
            <geboortedatum value="1964-08-02"/>
            <geslacht code="F" codeSystem="2.16.840.1.113883.5.1"/>
         </patient>
         <medicamenteuze_behandeling conceptId="2.16.840.1.113883.2.4.3.11.60.20.77.2.3.22092">
            <identificatie value="OH-MBH-1551446587306-100008363"
                           root="2.16.840.1.113883.2.4.6.6.90000258.1.100008363"
                           conceptId="2.16.840.1.113883.2.4.3.11.60.20.77.2.3.22093"/>
            <medicatieafspraak conceptId="2.16.840.1.113883.2.4.3.11.60.20.77.2.3.9580">
               <gebruiksperiode_start value="2018-01-29T00:00:00" conceptId="1.2.3.4.5.12345.9580.1"/>
               <gebruiksperiode_eind value="2018-02-12T23:59:59" conceptId="1.2.3.4.5.12345.9580.2"/>
               <identificatie value="14996"
                              root="2.16.840.1.113883.2.4.6.6.90000258.4.4"
                              conceptId="2.16.840.1.113883.2.4.3.11.60.20.77.2.3.19758"/>
               <afspraakdatum value="2018-01-29"
                              conceptId="2.16.840.1.113883.2.4.3.11.60.20.77.2.3.19757"/>
               <relaties_ketenzorg conceptId="2.16.840.1.113883.2.4.3.11.60.20.77.2.3.24024">
                  <identificatie_contactmoment value="996624"
                                               root="2.16.840.1.113883.2.4.6.6.90000258.4.1"
                                               conceptId="2.16.840.1.113883.2.4.3.11.60.20.77.2.3.24026"/>
               </relaties_ketenzorg>
               <voorschrijver conceptId="2.16.840.1.113883.2.4.3.11.60.20.77.2.3.1030">
                  <zorgverlener conceptId="2.16.840.1.113883.2.4.3.11.60.20.77.2.3.19835">
                     <zorgverlener_identificatienummer value="900013866"
                                                       root="2.16.528.1.1007.3.1"
                                                       conceptId="2.16.840.1.113883.2.4.3.11.60.20.77.2.3.19836"/>
                     <naamgegevens conceptId="2.16.840.1.113883.2.4.3.11.60.20.77.2.3.19837">
                        <naamgegevens conceptId="2.16.840.1.113883.2.4.3.11.60.20.77.2.3.19838">
                           <naamgebruik code="UNK"
                                        codeSystem="2.16.840.1.113883.5.1008"
                                        displayName="Unknown"
                                        conceptId="2.16.840.1.113883.2.4.3.11.60.20.77.2.3.19842"/>
                           <geslachtsnaam conceptId="2.16.840.1.113883.2.4.3.11.60.20.77.2.3.19843">
                              <achternaam value="Huisarts 1"
                                          conceptId="2.16.840.1.113883.2.4.3.11.60.20.77.2.3.19845"/>
                           </geslachtsnaam>
                        </naamgegevens>
                     </naamgegevens>
                     <specialisme code="01.015"
                                  codeSystem="2.16.840.1.113883.2.4.15.111"
                                  displayName="Huisarts"
                                  conceptId="2.16.840.1.113883.2.4.3.11.60.20.77.2.3.19849"/>
                     <zorgaanbieder conceptId="2.16.840.1.113883.2.4.3.11.60.20.77.2.3.19871">
                        <zorgaanbieder_identificatienummer value="90000381"
                                                           root="2.16.528.1.1007.3.3"
                                                           conceptId="2.16.840.1.113883.2.4.3.11.60.20.77.2.3.19873"/>
                        <organisatie_naam value="Tést Zorginstelling 04"
                                          conceptId="2.16.840.1.113883.2.4.3.11.60.20.77.2.3.19874"/>
                        <adresgegevens>
                           <straat value="Valkendael 45"/>
                           <postcode value="6245 HK"/>
                           <woonplaats value="Maastricht"/>
                           <land value="Nederland"/>
                           <adres_soort code="WP"
                                        codeSystem="2.16.840.1.113883.5.1119"
                                        displayName="Werkadres"/>
                        </adresgegevens>
                     </zorgaanbieder>
                  </zorgverlener>
               </voorschrijver>
               <reden_wijzigen_of_staken code="OTH"
                                         codeSystem="2.16.840.1.113883.5.1008"
                                         displayName="overig"
                                         originalText="Volgens afspraak"
                                         conceptId="2.16.840.1.113883.2.4.3.11.60.20.77.2.3.22094"/>
               <reden_van_voorschrijven conceptId="2.16.840.1.113883.2.4.3.11.60.20.77.2.3.23133">
                  <probleem conceptId="2.16.840.1.113883.2.4.3.11.60.20.77.2.3.23134">
                     <probleem_naam code="D02"
                                    codeSystem="2.16.840.1.113883.2.4.4.31.1"
                                    codeSystemName="ICPC-1-NL"
                                    displayName="Maagpijn"
                                    conceptId="2.16.840.1.113883.2.4.3.11.60.20.77.2.3.23136"/>
                  </probleem>
               </reden_van_voorschrijven>
               <afgesproken_geneesmiddel conceptId="2.16.840.1.113883.2.4.3.11.60.20.77.2.3.19925">
                  <product conceptId="2.16.840.1.113883.2.4.3.11.60.20.77.2.3.22603">
                     <product_code code="43044"
                                   codeSystem="2.16.840.1.113883.2.4.4.10"
                                   codeSystemName="PRK"
                                   displayName="PANTOPRAZOL TABLET MSR 40MG"
                                   conceptId="2.16.840.1.113883.2.4.3.11.60.20.77.2.3.22604"/>
                     <product_code code="96938"
                                   codeSystem="2.16.840.1.113883.2.4.4.1"
                                   codeSystemName="GPK"
                                   displayName="PANTOPRAZOL TABLET MSR 40MG"
                                   conceptId="2.16.840.1.113883.2.4.3.11.60.20.77.2.3.22604"/>
                  </product>
               </afgesproken_geneesmiddel>
               <gebruiksinstructie conceptId="2.16.840.1.113883.2.4.3.11.60.20.77.2.3.23240">
                  <omschrijving value="1 keer per dag 1 tablet"
                                conceptId="2.16.840.1.113883.2.4.3.11.60.20.77.2.3.23241"/>
                  <toedieningsweg code="9"
                                  codeSystem="2.16.840.1.113883.2.4.4.9"
                                  displayName="ORAAL"
                                  conceptId="2.16.840.1.113883.2.4.3.11.60.20.77.2.3.23242"/>
                  <doseerinstructie conceptId="2.16.840.1.113883.2.4.3.11.60.20.77.2.3.23245">
                     <volgnummer value="1" conceptId="2.16.840.1.113883.2.4.3.11.60.20.77.2.3.23246"/>
                     <doseerduur value="14"
                                 unit="dag"
                                 conceptId="2.16.840.1.113883.2.4.3.11.60.20.77.2.3.23247"/>
                     <dosering conceptId="2.16.840.1.113883.2.4.3.11.60.20.77.2.3.23248">
                        <keerdosis conceptId="2.16.840.1.113883.2.4.3.11.60.20.77.2.3.23249">
                           <aantal conceptId="2.16.840.1.113883.2.4.3.11.60.20.77.2.3.23250">
                              <vaste_waarde value="1" conceptId="2.16.840.1.113883.2.4.3.11.60.20.77.2.3.23252"/>
                           </aantal>
                           <eenheid code="245"
                                    codeSystem="2.16.840.1.113883.2.4.4.1.900.2"
                                    displayName="STUK"
                                    conceptId="2.16.840.1.113883.2.4.3.11.60.20.77.2.3.23254"/>
                        </keerdosis>
                        <toedieningsschema conceptId="2.16.840.1.113883.2.4.3.11.60.20.77.2.3.23256">
                           <interval value="1"
                                     unit="dag"
                                     conceptId="2.16.840.1.113883.2.4.3.11.60.20.77.2.3.23263"/>
                        </toedieningsschema>
                     </dosering>
                  </doseerinstructie>
               </gebruiksinstructie>
               <kopie_indicator value="false" conceptId="2.16.840.1.113883.2.4.3.11.60.20.77.2.3.23411"/>
            </medicatieafspraak>
         </medicamenteuze_behandeling>
         <medicamenteuze_behandeling conceptId="2.16.840.1.113883.2.4.3.11.60.20.77.2.3.22092">
            <identificatie value="OH-MBH-1551446587416-100008364"
                           root="2.16.840.1.113883.2.4.6.6.90000258.1.100008364"
                           conceptId="2.16.840.1.113883.2.4.3.11.60.20.77.2.3.22093"/>
            <medicatieafspraak conceptId="2.16.840.1.113883.2.4.3.11.60.20.77.2.3.9580">
               <gebruiksperiode_start value="2019-02-03T00:00:00" conceptId="1.2.3.4.5.12345.9580.1"/>
               <gebruiksperiode_eind value="2019-02-07T23:59:59" conceptId="1.2.3.4.5.12345.9580.2"/>
               <identificatie value="14997"
                              root="2.16.840.1.113883.2.4.6.6.90000258.4.4"
                              conceptId="2.16.840.1.113883.2.4.3.11.60.20.77.2.3.19758"/>
               <afspraakdatum value="2019-02-03"
                              conceptId="2.16.840.1.113883.2.4.3.11.60.20.77.2.3.19757"/>
               <relaties_ketenzorg conceptId="2.16.840.1.113883.2.4.3.11.60.20.77.2.3.24024">
                  <identificatie_contactmoment value="996625"
                                               root="2.16.840.1.113883.2.4.6.6.90000258.4.1"
                                               conceptId="2.16.840.1.113883.2.4.3.11.60.20.77.2.3.24026"/>
               </relaties_ketenzorg>
               <voorschrijver conceptId="2.16.840.1.113883.2.4.3.11.60.20.77.2.3.1030">
                  <zorgverlener conceptId="2.16.840.1.113883.2.4.3.11.60.20.77.2.3.19835">
                     <zorgverlener_identificatienummer value="900013866"
                                                       root="2.16.528.1.1007.3.1"
                                                       conceptId="2.16.840.1.113883.2.4.3.11.60.20.77.2.3.19836"/>
                     <naamgegevens conceptId="2.16.840.1.113883.2.4.3.11.60.20.77.2.3.19837">
                        <naamgegevens conceptId="2.16.840.1.113883.2.4.3.11.60.20.77.2.3.19838">
                           <naamgebruik code="UNK"
                                        codeSystem="2.16.840.1.113883.5.1008"
                                        displayName="Unknown"
                                        conceptId="2.16.840.1.113883.2.4.3.11.60.20.77.2.3.19842"/>
                           <geslachtsnaam conceptId="2.16.840.1.113883.2.4.3.11.60.20.77.2.3.19843">
                              <achternaam value="Huisarts 1"
                                          conceptId="2.16.840.1.113883.2.4.3.11.60.20.77.2.3.19845"/>
                           </geslachtsnaam>
                        </naamgegevens>
                     </naamgegevens>
                     <specialisme code="01.015"
                                  codeSystem="2.16.840.1.113883.2.4.15.111"
                                  displayName="Huisarts"
                                  conceptId="2.16.840.1.113883.2.4.3.11.60.20.77.2.3.19849"/>
                     <zorgaanbieder conceptId="2.16.840.1.113883.2.4.3.11.60.20.77.2.3.19871">
                        <zorgaanbieder_identificatienummer value="90000381"
                                                           root="2.16.528.1.1007.3.3"
                                                           conceptId="2.16.840.1.113883.2.4.3.11.60.20.77.2.3.19873"/>
                        <organisatie_naam value="Tést Zorginstelling 04"
                                          conceptId="2.16.840.1.113883.2.4.3.11.60.20.77.2.3.19874"/>
                        <adresgegevens>
                           <straat value="Valkendael 45"/>
                           <postcode value="6245 HK"/>
                           <woonplaats value="Maastricht"/>
                           <land value="Nederland"/>
                           <adres_soort code="WP"
                                        codeSystem="2.16.840.1.113883.5.1119"
                                        displayName="Werkadres"/>
                        </adresgegevens>
                     </zorgaanbieder>
                  </zorgverlener>
               </voorschrijver>
               <reden_wijzigen_of_staken code="OTH"
                                         codeSystem="2.16.840.1.113883.5.1008"
                                         displayName="overig"
                                         originalText="Volgens afspraak"
                                         conceptId="2.16.840.1.113883.2.4.3.11.60.20.77.2.3.22094"/>
               <reden_van_voorschrijven conceptId="2.16.840.1.113883.2.4.3.11.60.20.77.2.3.23133">
                  <probleem conceptId="2.16.840.1.113883.2.4.3.11.60.20.77.2.3.23134">
                     <probleem_naam code="R95"
                                    codeSystem="2.16.840.1.113883.2.4.4.31.1"
                                    codeSystemName="ICPC-1-NL"
                                    displayName="Emfyseem/COPD"
                                    conceptId="2.16.840.1.113883.2.4.3.11.60.20.77.2.3.23136"/>
                  </probleem>
               </reden_van_voorschrijven>
               <afgesproken_geneesmiddel conceptId="2.16.840.1.113883.2.4.3.11.60.20.77.2.3.19925">
                  <product conceptId="2.16.840.1.113883.2.4.3.11.60.20.77.2.3.22603">
                     <product_code code="67903"
                                   codeSystem="2.16.840.1.113883.2.4.4.10"
                                   codeSystemName="PRK"
                                   displayName="PARACETAMOL TABLET  500MG"
                                   conceptId="2.16.840.1.113883.2.4.3.11.60.20.77.2.3.22604"/>
                     <product_code code="2194"
                                   codeSystem="2.16.840.1.113883.2.4.4.1"
                                   codeSystemName="GPK"
                                   displayName="PARACETAMOL TABLET  500MG"
                                   conceptId="2.16.840.1.113883.2.4.3.11.60.20.77.2.3.22604"/>
                  </product>
               </afgesproken_geneesmiddel>
               <gebruiksinstructie conceptId="2.16.840.1.113883.2.4.3.11.60.20.77.2.3.23240">
                  <omschrijving value="6 keer per dag 1 tablet, Zo nodig"
                                conceptId="2.16.840.1.113883.2.4.3.11.60.20.77.2.3.23241"/>
                  <toedieningsweg code="9"
                                  codeSystem="2.16.840.1.113883.2.4.4.9"
                                  displayName="ORAAL"
                                  conceptId="2.16.840.1.113883.2.4.3.11.60.20.77.2.3.23242"/>
                  <aanvullende_instructie code="1137"
                                          codeSystem="2.16.840.1.113883.2.4.4.5"
                                          displayName="Zo nodig"
                                          conceptId="2.16.840.1.113883.2.4.3.11.60.20.77.2.3.23243"/>
                  <doseerinstructie conceptId="2.16.840.1.113883.2.4.3.11.60.20.77.2.3.23245">
                     <volgnummer value="1" conceptId="2.16.840.1.113883.2.4.3.11.60.20.77.2.3.23246"/>
                     <doseerduur value="4"
                                 unit="dag"
                                 conceptId="2.16.840.1.113883.2.4.3.11.60.20.77.2.3.23247"/>
                     <dosering conceptId="2.16.840.1.113883.2.4.3.11.60.20.77.2.3.23248">
                        <keerdosis conceptId="2.16.840.1.113883.2.4.3.11.60.20.77.2.3.23249">
                           <aantal conceptId="2.16.840.1.113883.2.4.3.11.60.20.77.2.3.23250">
                              <vaste_waarde value="1" conceptId="2.16.840.1.113883.2.4.3.11.60.20.77.2.3.23252"/>
                           </aantal>
                           <eenheid code="245"
                                    codeSystem="2.16.840.1.113883.2.4.4.1.900.2"
                                    displayName="STUK"
                                    conceptId="2.16.840.1.113883.2.4.3.11.60.20.77.2.3.23254"/>
                        </keerdosis>
                        <toedieningsschema conceptId="2.16.840.1.113883.2.4.3.11.60.20.77.2.3.23256">
                           <interval value="0.1667"
                                     unit="dag"
                                     conceptId="2.16.840.1.113883.2.4.3.11.60.20.77.2.3.23263"/>
                        </toedieningsschema>
                        <zo_nodig conceptId="2.16.840.1.113883.2.4.3.11.60.20.77.2.3.23267">
                           <criterium conceptId="2.16.840.1.113883.2.4.3.11.60.20.77.2.3.23268">
                              <code conceptId="2.16.840.1.113883.2.4.3.11.60.20.77.2.3.23269"
                                    code="1137"
                                    codeSystem="2.16.840.1.113883.2.4.4.5"
                                    displayName="zo nodig"/>
                           </criterium>
                        </zo_nodig>
                     </dosering>
                  </doseerinstructie>
               </gebruiksinstructie>
               <kopie_indicator value="false" conceptId="2.16.840.1.113883.2.4.3.11.60.20.77.2.3.23411"/>
            </medicatieafspraak>
         </medicamenteuze_behandeling>
         <medicamenteuze_behandeling conceptId="2.16.840.1.113883.2.4.3.11.60.20.77.2.3.22092">
            <identificatie value="OH-MBH-1551446587464-100008365"
                           root="2.16.840.1.113883.2.4.6.6.90000258.1.100008365"
                           conceptId="2.16.840.1.113883.2.4.3.11.60.20.77.2.3.22093"/>
            <medicatieafspraak conceptId="2.16.840.1.113883.2.4.3.11.60.20.77.2.3.9580">
               <gebruiksperiode_start value="2019-02-03T00:00:00" conceptId="1.2.3.4.5.12345.9580.1"/>
               <gebruiksperiode_eind value="2019-03-04T23:59:59" conceptId="1.2.3.4.5.12345.9580.2"/>
               <identificatie value="14998"
                              root="2.16.840.1.113883.2.4.6.6.90000258.4.4"
                              conceptId="2.16.840.1.113883.2.4.3.11.60.20.77.2.3.19758"/>
               <afspraakdatum value="2019-02-03"
                              conceptId="2.16.840.1.113883.2.4.3.11.60.20.77.2.3.19757"/>
               <relaties_ketenzorg conceptId="2.16.840.1.113883.2.4.3.11.60.20.77.2.3.24024">
                  <identificatie_contactmoment value="996625"
                                               root="2.16.840.1.113883.2.4.6.6.90000258.4.1"
                                               conceptId="2.16.840.1.113883.2.4.3.11.60.20.77.2.3.24026"/>
               </relaties_ketenzorg>
               <voorschrijver conceptId="2.16.840.1.113883.2.4.3.11.60.20.77.2.3.1030">
                  <zorgverlener conceptId="2.16.840.1.113883.2.4.3.11.60.20.77.2.3.19835">
                     <zorgverlener_identificatienummer value="900013866"
                                                       root="2.16.528.1.1007.3.1"
                                                       conceptId="2.16.840.1.113883.2.4.3.11.60.20.77.2.3.19836"/>
                     <naamgegevens conceptId="2.16.840.1.113883.2.4.3.11.60.20.77.2.3.19837">
                        <naamgegevens conceptId="2.16.840.1.113883.2.4.3.11.60.20.77.2.3.19838">
                           <naamgebruik code="UNK"
                                        codeSystem="2.16.840.1.113883.5.1008"
                                        displayName="Unknown"
                                        conceptId="2.16.840.1.113883.2.4.3.11.60.20.77.2.3.19842"/>
                           <geslachtsnaam conceptId="2.16.840.1.113883.2.4.3.11.60.20.77.2.3.19843">
                              <achternaam value="Huisarts 1"
                                          conceptId="2.16.840.1.113883.2.4.3.11.60.20.77.2.3.19845"/>
                           </geslachtsnaam>
                        </naamgegevens>
                     </naamgegevens>
                     <specialisme code="01.015"
                                  codeSystem="2.16.840.1.113883.2.4.15.111"
                                  displayName="Huisarts"
                                  conceptId="2.16.840.1.113883.2.4.3.11.60.20.77.2.3.19849"/>
                     <zorgaanbieder conceptId="2.16.840.1.113883.2.4.3.11.60.20.77.2.3.19871">
                        <zorgaanbieder_identificatienummer value="90000381"
                                                           root="2.16.528.1.1007.3.3"
                                                           conceptId="2.16.840.1.113883.2.4.3.11.60.20.77.2.3.19873"/>
                        <organisatie_naam value="Tést Zorginstelling 04"
                                          conceptId="2.16.840.1.113883.2.4.3.11.60.20.77.2.3.19874"/>
                        <adresgegevens>
                           <straat value="Valkendael 45"/>
                           <postcode value="6245 HK"/>
                           <woonplaats value="Maastricht"/>
                           <land value="Nederland"/>
                           <adres_soort code="WP"
                                        codeSystem="2.16.840.1.113883.5.1119"
                                        displayName="Werkadres"/>
                        </adresgegevens>
                     </zorgaanbieder>
                  </zorgverlener>
               </voorschrijver>
               <reden_wijzigen_of_staken code="OTH"
                                         codeSystem="2.16.840.1.113883.5.1008"
                                         displayName="overig"
                                         originalText="Volgens afspraak"
                                         conceptId="2.16.840.1.113883.2.4.3.11.60.20.77.2.3.22094"/>
               <reden_van_voorschrijven conceptId="2.16.840.1.113883.2.4.3.11.60.20.77.2.3.23133">
                  <probleem conceptId="2.16.840.1.113883.2.4.3.11.60.20.77.2.3.23134">
                     <probleem_naam code="R95"
                                    codeSystem="2.16.840.1.113883.2.4.4.31.1"
                                    codeSystemName="ICPC-1-NL"
                                    displayName="Emfyseem/COPD"
                                    conceptId="2.16.840.1.113883.2.4.3.11.60.20.77.2.3.23136"/>
                  </probleem>
               </reden_van_voorschrijven>
               <afgesproken_geneesmiddel conceptId="2.16.840.1.113883.2.4.3.11.60.20.77.2.3.19925">
                  <product conceptId="2.16.840.1.113883.2.4.3.11.60.20.77.2.3.22603">
                     <product_code code="45632"
                                   codeSystem="2.16.840.1.113883.2.4.4.10"
                                   codeSystemName="PRK"
                                   displayName="FLUTICASON INHALATIEPOEDER 250UG/DO 60DO DISKUS"
                                   conceptId="2.16.840.1.113883.2.4.3.11.60.20.77.2.3.22604"/>
                     <product_code code="92495"
                                   codeSystem="2.16.840.1.113883.2.4.4.1"
                                   codeSystemName="GPK"
                                   displayName="FLUTICASON INHALATIEPOEDER 250UG/DO"
                                   conceptId="2.16.840.1.113883.2.4.3.11.60.20.77.2.3.22604"/>
                  </product>
               </afgesproken_geneesmiddel>
               <gebruiksinstructie conceptId="2.16.840.1.113883.2.4.3.11.60.20.77.2.3.23240">
                  <omschrijving value="2 keer per dag 1 inhalatie"
                                conceptId="2.16.840.1.113883.2.4.3.11.60.20.77.2.3.23241"/>
                  <toedieningsweg code="62"
                                  codeSystem="2.16.840.1.113883.2.4.4.9"
                                  displayName="INHALATIE"
                                  conceptId="2.16.840.1.113883.2.4.3.11.60.20.77.2.3.23242"/>
                  <doseerinstructie conceptId="2.16.840.1.113883.2.4.3.11.60.20.77.2.3.23245">
                     <volgnummer value="1" conceptId="2.16.840.1.113883.2.4.3.11.60.20.77.2.3.23246"/>
                     <doseerduur value="29"
                                 unit="dag"
                                 conceptId="2.16.840.1.113883.2.4.3.11.60.20.77.2.3.23247"/>
                     <dosering conceptId="2.16.840.1.113883.2.4.3.11.60.20.77.2.3.23248">
                        <keerdosis conceptId="2.16.840.1.113883.2.4.3.11.60.20.77.2.3.23249">
                           <aantal conceptId="2.16.840.1.113883.2.4.3.11.60.20.77.2.3.23250">
                              <vaste_waarde value="1" conceptId="2.16.840.1.113883.2.4.3.11.60.20.77.2.3.23252"/>
                           </aantal>
                           <eenheid code="208"
                                    codeSystem="2.16.840.1.113883.2.4.4.1.900.2"
                                    displayName="DOSIS"
                                    conceptId="2.16.840.1.113883.2.4.3.11.60.20.77.2.3.23254"/>
                        </keerdosis>
                        <toedieningsschema conceptId="2.16.840.1.113883.2.4.3.11.60.20.77.2.3.23256">
                           <interval value="0.5"
                                     unit="dag"
                                     conceptId="2.16.840.1.113883.2.4.3.11.60.20.77.2.3.23263"/>
                        </toedieningsschema>
                     </dosering>
                  </doseerinstructie>
               </gebruiksinstructie>
               <kopie_indicator value="false" conceptId="2.16.840.1.113883.2.4.3.11.60.20.77.2.3.23411"/>
            </medicatieafspraak>
         </medicamenteuze_behandeling>
         <medicamenteuze_behandeling conceptId="2.16.840.1.113883.2.4.3.11.60.20.77.2.3.22092">
            <identificatie value="OH-MBH-1551446587502-100008366"
                           root="2.16.840.1.113883.2.4.6.6.90000258.1.100008366"
                           conceptId="2.16.840.1.113883.2.4.3.11.60.20.77.2.3.22093"/>
            <medicatieafspraak conceptId="2.16.840.1.113883.2.4.3.11.60.20.77.2.3.9580">
               <gebruiksperiode_start value="2019-02-06T00:00:00" conceptId="1.2.3.4.5.12345.9580.1"/>
               <gebruiksperiode_eind value="2019-02-12T23:59:59" conceptId="1.2.3.4.5.12345.9580.2"/>
               <identificatie value="14999"
                              root="2.16.840.1.113883.2.4.6.6.90000258.4.4"
                              conceptId="2.16.840.1.113883.2.4.3.11.60.20.77.2.3.19758"/>
               <afspraakdatum value="2019-02-06"
                              conceptId="2.16.840.1.113883.2.4.3.11.60.20.77.2.3.19757"/>
               <relaties_ketenzorg conceptId="2.16.840.1.113883.2.4.3.11.60.20.77.2.3.24024">
                  <identificatie_contactmoment value="996626"
                                               root="2.16.840.1.113883.2.4.6.6.90000258.4.1"
                                               conceptId="2.16.840.1.113883.2.4.3.11.60.20.77.2.3.24026"/>
               </relaties_ketenzorg>
               <voorschrijver conceptId="2.16.840.1.113883.2.4.3.11.60.20.77.2.3.1030">
                  <zorgverlener conceptId="2.16.840.1.113883.2.4.3.11.60.20.77.2.3.19835">
                     <zorgverlener_identificatienummer value="900013866"
                                                       root="2.16.528.1.1007.3.1"
                                                       conceptId="2.16.840.1.113883.2.4.3.11.60.20.77.2.3.19836"/>
                     <naamgegevens conceptId="2.16.840.1.113883.2.4.3.11.60.20.77.2.3.19837">
                        <naamgegevens conceptId="2.16.840.1.113883.2.4.3.11.60.20.77.2.3.19838">
                           <naamgebruik code="UNK"
                                        codeSystem="2.16.840.1.113883.5.1008"
                                        displayName="Unknown"
                                        conceptId="2.16.840.1.113883.2.4.3.11.60.20.77.2.3.19842"/>
                           <geslachtsnaam conceptId="2.16.840.1.113883.2.4.3.11.60.20.77.2.3.19843">
                              <achternaam value="Huisarts 1"
                                          conceptId="2.16.840.1.113883.2.4.3.11.60.20.77.2.3.19845"/>
                           </geslachtsnaam>
                        </naamgegevens>
                     </naamgegevens>
                     <specialisme code="01.015"
                                  codeSystem="2.16.840.1.113883.2.4.15.111"
                                  displayName="Huisarts"
                                  conceptId="2.16.840.1.113883.2.4.3.11.60.20.77.2.3.19849"/>
                     <zorgaanbieder conceptId="2.16.840.1.113883.2.4.3.11.60.20.77.2.3.19871">
                        <zorgaanbieder_identificatienummer value="90000381"
                                                           root="2.16.528.1.1007.3.3"
                                                           conceptId="2.16.840.1.113883.2.4.3.11.60.20.77.2.3.19873"/>
                        <organisatie_naam value="Tést Zorginstelling 04"
                                          conceptId="2.16.840.1.113883.2.4.3.11.60.20.77.2.3.19874"/>
                        <adresgegevens>
                           <straat value="Valkendael 45"/>
                           <postcode value="6245 HK"/>
                           <woonplaats value="Maastricht"/>
                           <land value="Nederland"/>
                           <adres_soort code="WP"
                                        codeSystem="2.16.840.1.113883.5.1119"
                                        displayName="Werkadres"/>
                        </adresgegevens>
                     </zorgaanbieder>
                  </zorgverlener>
               </voorschrijver>
               <reden_wijzigen_of_staken code="OTH"
                                         codeSystem="2.16.840.1.113883.5.1008"
                                         displayName="overig"
                                         originalText="Volgens afspraak"
                                         conceptId="2.16.840.1.113883.2.4.3.11.60.20.77.2.3.22094"/>
               <reden_van_voorschrijven conceptId="2.16.840.1.113883.2.4.3.11.60.20.77.2.3.23133">
                  <probleem conceptId="2.16.840.1.113883.2.4.3.11.60.20.77.2.3.23134">
                     <probleem_naam code="R95"
                                    codeSystem="2.16.840.1.113883.2.4.4.31.1"
                                    codeSystemName="ICPC-1-NL"
                                    displayName="Emfyseem/COPD"
                                    conceptId="2.16.840.1.113883.2.4.3.11.60.20.77.2.3.23136"/>
                  </probleem>
               </reden_van_voorschrijven>
               <afgesproken_geneesmiddel conceptId="2.16.840.1.113883.2.4.3.11.60.20.77.2.3.19925">
                  <product conceptId="2.16.840.1.113883.2.4.3.11.60.20.77.2.3.22603">
                     <product_code code="17809"
                                   codeSystem="2.16.840.1.113883.2.4.4.10"
                                   codeSystemName="PRK"
                                   displayName="AMOXICILLINE/CLAVULAANZUUR TABLET 500/125MG"
                                   conceptId="2.16.840.1.113883.2.4.3.11.60.20.77.2.3.22604"/>
                     <product_code code="43079"
                                   codeSystem="2.16.840.1.113883.2.4.4.1"
                                   codeSystemName="GPK"
                                   displayName="AMOXICILLINE/CLAVULAANZUUR TABLET 500/125MG"
                                   conceptId="2.16.840.1.113883.2.4.3.11.60.20.77.2.3.22604"/>
                  </product>
               </afgesproken_geneesmiddel>
               <gebruiksinstructie conceptId="2.16.840.1.113883.2.4.3.11.60.20.77.2.3.23240">
                  <omschrijving value="3 keer per dag 1 tablet"
                                conceptId="2.16.840.1.113883.2.4.3.11.60.20.77.2.3.23241"/>
                  <toedieningsweg code="9"
                                  codeSystem="2.16.840.1.113883.2.4.4.9"
                                  displayName="ORAAL"
                                  conceptId="2.16.840.1.113883.2.4.3.11.60.20.77.2.3.23242"/>
                  <doseerinstructie conceptId="2.16.840.1.113883.2.4.3.11.60.20.77.2.3.23245">
                     <volgnummer value="1" conceptId="2.16.840.1.113883.2.4.3.11.60.20.77.2.3.23246"/>
                     <doseerduur value="6"
                                 unit="dag"
                                 conceptId="2.16.840.1.113883.2.4.3.11.60.20.77.2.3.23247"/>
                     <dosering conceptId="2.16.840.1.113883.2.4.3.11.60.20.77.2.3.23248">
                        <keerdosis conceptId="2.16.840.1.113883.2.4.3.11.60.20.77.2.3.23249">
                           <aantal conceptId="2.16.840.1.113883.2.4.3.11.60.20.77.2.3.23250">
                              <vaste_waarde value="1" conceptId="2.16.840.1.113883.2.4.3.11.60.20.77.2.3.23252"/>
                           </aantal>
                           <eenheid code="245"
                                    codeSystem="2.16.840.1.113883.2.4.4.1.900.2"
                                    displayName="STUK"
                                    conceptId="2.16.840.1.113883.2.4.3.11.60.20.77.2.3.23254"/>
                        </keerdosis>
                        <toedieningsschema conceptId="2.16.840.1.113883.2.4.3.11.60.20.77.2.3.23256">
                           <interval value="0.3333"
                                     unit="dag"
                                     conceptId="2.16.840.1.113883.2.4.3.11.60.20.77.2.3.23263"/>
                        </toedieningsschema>
                     </dosering>
                  </doseerinstructie>
               </gebruiksinstructie>
               <kopie_indicator value="false" conceptId="2.16.840.1.113883.2.4.3.11.60.20.77.2.3.23411"/>
            </medicatieafspraak>
         </medicamenteuze_behandeling>
         <medicamenteuze_behandeling conceptId="2.16.840.1.113883.2.4.3.11.60.20.77.2.3.22092">
            <identificatie value="OH-MBH-1551446587544-100008367"
                           root="2.16.840.1.113883.2.4.6.6.90000258.1.100008367"
                           conceptId="2.16.840.1.113883.2.4.3.11.60.20.77.2.3.22093"/>
            <medicatieafspraak conceptId="2.16.840.1.113883.2.4.3.11.60.20.77.2.3.9580">
               <gebruiksperiode_start value="2019-02-06T00:00:00" conceptId="1.2.3.4.5.12345.9580.1"/>
               <identificatie value="15000"
                              root="2.16.840.1.113883.2.4.6.6.90000258.4.4"
                              conceptId="2.16.840.1.113883.2.4.3.11.60.20.77.2.3.19758"/>
               <afspraakdatum value="2019-02-06"
                              conceptId="2.16.840.1.113883.2.4.3.11.60.20.77.2.3.19757"/>
               <relaties_ketenzorg conceptId="2.16.840.1.113883.2.4.3.11.60.20.77.2.3.24024">
                  <identificatie_contactmoment value="996626"
                                               root="2.16.840.1.113883.2.4.6.6.90000258.4.1"
                                               conceptId="2.16.840.1.113883.2.4.3.11.60.20.77.2.3.24026"/>
               </relaties_ketenzorg>
               <voorschrijver conceptId="2.16.840.1.113883.2.4.3.11.60.20.77.2.3.1030">
                  <zorgverlener conceptId="2.16.840.1.113883.2.4.3.11.60.20.77.2.3.19835">
                     <zorgverlener_identificatienummer value="900013866"
                                                       root="2.16.528.1.1007.3.1"
                                                       conceptId="2.16.840.1.113883.2.4.3.11.60.20.77.2.3.19836"/>
                     <naamgegevens conceptId="2.16.840.1.113883.2.4.3.11.60.20.77.2.3.19837">
                        <naamgegevens conceptId="2.16.840.1.113883.2.4.3.11.60.20.77.2.3.19838">
                           <naamgebruik code="UNK"
                                        codeSystem="2.16.840.1.113883.5.1008"
                                        displayName="Unknown"
                                        conceptId="2.16.840.1.113883.2.4.3.11.60.20.77.2.3.19842"/>
                           <geslachtsnaam conceptId="2.16.840.1.113883.2.4.3.11.60.20.77.2.3.19843">
                              <achternaam value="Huisarts 1"
                                          conceptId="2.16.840.1.113883.2.4.3.11.60.20.77.2.3.19845"/>
                           </geslachtsnaam>
                        </naamgegevens>
                     </naamgegevens>
                     <specialisme code="01.015"
                                  codeSystem="2.16.840.1.113883.2.4.15.111"
                                  displayName="Huisarts"
                                  conceptId="2.16.840.1.113883.2.4.3.11.60.20.77.2.3.19849"/>
                     <zorgaanbieder conceptId="2.16.840.1.113883.2.4.3.11.60.20.77.2.3.19871">
                        <zorgaanbieder_identificatienummer value="90000381"
                                                           root="2.16.528.1.1007.3.3"
                                                           conceptId="2.16.840.1.113883.2.4.3.11.60.20.77.2.3.19873"/>
                        <organisatie_naam value="Tést Zorginstelling 04"
                                          conceptId="2.16.840.1.113883.2.4.3.11.60.20.77.2.3.19874"/>
                        <adresgegevens>
                           <straat value="Valkendael 45"/>
                           <postcode value="6245 HK"/>
                           <woonplaats value="Maastricht"/>
                           <land value="Nederland"/>
                           <adres_soort code="WP"
                                        codeSystem="2.16.840.1.113883.5.1119"
                                        displayName="Werkadres"/>
                        </adresgegevens>
                     </zorgaanbieder>
                  </zorgverlener>
               </voorschrijver>
               <reden_wijzigen_of_staken code="OTH"
                                         codeSystem="2.16.840.1.113883.5.1008"
                                         displayName="overig"
                                         originalText="Volgens afspraak"
                                         conceptId="2.16.840.1.113883.2.4.3.11.60.20.77.2.3.22094"/>
               <reden_van_voorschrijven conceptId="2.16.840.1.113883.2.4.3.11.60.20.77.2.3.23133">
                  <probleem conceptId="2.16.840.1.113883.2.4.3.11.60.20.77.2.3.23134">
                     <probleem_naam code="R95"
                                    codeSystem="2.16.840.1.113883.2.4.4.31.1"
                                    codeSystemName="ICPC-1-NL"
                                    displayName="Emfyseem/COPD"
                                    conceptId="2.16.840.1.113883.2.4.3.11.60.20.77.2.3.23136"/>
                  </probleem>
               </reden_van_voorschrijven>
               <afgesproken_geneesmiddel conceptId="2.16.840.1.113883.2.4.3.11.60.20.77.2.3.19925">
                  <product conceptId="2.16.840.1.113883.2.4.3.11.60.20.77.2.3.22603">
                     <product_code code="73040"
                                   codeSystem="2.16.840.1.113883.2.4.4.10"
                                   codeSystemName="PRK"
                                   displayName="SALBUTAMOL INHALATIEPOEDER 100UG/DO PATR 200DO"
                                   conceptId="2.16.840.1.113883.2.4.3.11.60.20.77.2.3.22604"/>
                     <product_code code="99473"
                                   codeSystem="2.16.840.1.113883.2.4.4.1"
                                   codeSystemName="GPK"
                                   displayName="SALBUTAMOL INHALATIEPOEDER 100UG/DO"
                                   conceptId="2.16.840.1.113883.2.4.3.11.60.20.77.2.3.22604"/>
                  </product>
               </afgesproken_geneesmiddel>
               <gebruiksinstructie conceptId="2.16.840.1.113883.2.4.3.11.60.20.77.2.3.23240">
                  <omschrijving value="3 tot 4 keer per dag 1 inhalatie"
                                conceptId="2.16.840.1.113883.2.4.3.11.60.20.77.2.3.23241"/>
                  <toedieningsweg code="62"
                                  codeSystem="2.16.840.1.113883.2.4.4.9"
                                  displayName="INHALATIE"
                                  conceptId="2.16.840.1.113883.2.4.3.11.60.20.77.2.3.23242"/>
                  <doseerinstructie conceptId="2.16.840.1.113883.2.4.3.11.60.20.77.2.3.23245">
                     <volgnummer value="1" conceptId="2.16.840.1.113883.2.4.3.11.60.20.77.2.3.23246"/>
                     <dosering conceptId="2.16.840.1.113883.2.4.3.11.60.20.77.2.3.23248">
                        <keerdosis conceptId="2.16.840.1.113883.2.4.3.11.60.20.77.2.3.23249">
                           <aantal conceptId="2.16.840.1.113883.2.4.3.11.60.20.77.2.3.23250">
                              <vaste_waarde value="1" conceptId="2.16.840.1.113883.2.4.3.11.60.20.77.2.3.23252"/>
                           </aantal>
                           <eenheid code="208"
                                    codeSystem="2.16.840.1.113883.2.4.4.1.900.2"
                                    displayName="DOSIS"
                                    conceptId="2.16.840.1.113883.2.4.3.11.60.20.77.2.3.23254"/>
                        </keerdosis>
                        <toedieningsschema conceptId="2.16.840.1.113883.2.4.3.11.60.20.77.2.3.23256">
                           <frequentie conceptId="2.16.840.1.113883.2.4.3.11.60.20.77.2.3.23257">
                              <aantal conceptId="2.16.840.1.113883.2.4.3.11.60.20.77.2.3.23258">
                                 <min value="3" conceptId="2.16.840.1.113883.2.4.3.11.60.20.77.2.3.23259"/>
                                 <max value="4" conceptId="2.16.840.1.113883.2.4.3.11.60.20.77.2.3.23261"/>
                              </aantal>
                              <tijdseenheid value="1.0"
                                            unit="dag"
                                            conceptId="2.16.840.1.113883.2.4.3.11.60.20.77.2.3.23262"/>
                           </frequentie>
                        </toedieningsschema>
                     </dosering>
                  </doseerinstructie>
               </gebruiksinstructie>
               <kopie_indicator value="false" conceptId="2.16.840.1.113883.2.4.3.11.60.20.77.2.3.23411"/>
            </medicatieafspraak>
         </medicamenteuze_behandeling>
         <medicamenteuze_behandeling conceptId="2.16.840.1.113883.2.4.3.11.60.20.77.2.3.22092">
            <identificatie value="OH-MBH-1551446587634-100008369"
                           root="2.16.840.1.113883.2.4.6.6.90000258.1.100008369"
                           conceptId="2.16.840.1.113883.2.4.3.11.60.20.77.2.3.22093"/>
            <medicatieafspraak conceptId="2.16.840.1.113883.2.4.3.11.60.20.77.2.3.9580">
               <gebruiksperiode_start value="2019-02-08T00:00:00" conceptId="1.2.3.4.5.12345.9580.1"/>
               <gebruiksperiode_eind value="2019-05-08T23:59:59" conceptId="1.2.3.4.5.12345.9580.2"/>
               <identificatie value="15002"
                              root="2.16.840.1.113883.2.4.6.6.90000258.4.4"
                              conceptId="2.16.840.1.113883.2.4.3.11.60.20.77.2.3.19758"/>
               <afspraakdatum value="2019-02-08"
                              conceptId="2.16.840.1.113883.2.4.3.11.60.20.77.2.3.19757"/>
               <relaties_ketenzorg conceptId="2.16.840.1.113883.2.4.3.11.60.20.77.2.3.24024">
                  <identificatie_contactmoment value="996627"
                                               root="2.16.840.1.113883.2.4.6.6.90000258.4.1"
                                               conceptId="2.16.840.1.113883.2.4.3.11.60.20.77.2.3.24026"/>
               </relaties_ketenzorg>
               <voorschrijver conceptId="2.16.840.1.113883.2.4.3.11.60.20.77.2.3.1030">
                  <zorgverlener conceptId="2.16.840.1.113883.2.4.3.11.60.20.77.2.3.19835">
                     <zorgverlener_identificatienummer value="900013866"
                                                       root="2.16.528.1.1007.3.1"
                                                       conceptId="2.16.840.1.113883.2.4.3.11.60.20.77.2.3.19836"/>
                     <naamgegevens conceptId="2.16.840.1.113883.2.4.3.11.60.20.77.2.3.19837">
                        <naamgegevens conceptId="2.16.840.1.113883.2.4.3.11.60.20.77.2.3.19838">
                           <naamgebruik code="UNK"
                                        codeSystem="2.16.840.1.113883.5.1008"
                                        displayName="Unknown"
                                        conceptId="2.16.840.1.113883.2.4.3.11.60.20.77.2.3.19842"/>
                           <geslachtsnaam conceptId="2.16.840.1.113883.2.4.3.11.60.20.77.2.3.19843">
                              <achternaam value="Huisarts 1"
                                          conceptId="2.16.840.1.113883.2.4.3.11.60.20.77.2.3.19845"/>
                           </geslachtsnaam>
                        </naamgegevens>
                     </naamgegevens>
                     <specialisme code="01.015"
                                  codeSystem="2.16.840.1.113883.2.4.15.111"
                                  displayName="Huisarts"
                                  conceptId="2.16.840.1.113883.2.4.3.11.60.20.77.2.3.19849"/>
                     <zorgaanbieder conceptId="2.16.840.1.113883.2.4.3.11.60.20.77.2.3.19871">
                        <zorgaanbieder_identificatienummer value="90000381"
                                                           root="2.16.528.1.1007.3.3"
                                                           conceptId="2.16.840.1.113883.2.4.3.11.60.20.77.2.3.19873"/>
                        <organisatie_naam value="Tést Zorginstelling 04"
                                          conceptId="2.16.840.1.113883.2.4.3.11.60.20.77.2.3.19874"/>
                        <adresgegevens>
                           <straat value="Valkendael 45"/>
                           <postcode value="6245 HK"/>
                           <woonplaats value="Maastricht"/>
                           <land value="Nederland"/>
                           <adres_soort code="WP"
                                        codeSystem="2.16.840.1.113883.5.1119"
                                        displayName="Werkadres"/>
                        </adresgegevens>
                     </zorgaanbieder>
                  </zorgverlener>
               </voorschrijver>
               <reden_wijzigen_of_staken code="OTH"
                                         codeSystem="2.16.840.1.113883.5.1008"
                                         displayName="overig"
                                         originalText="Volgens afspraak"
                                         conceptId="2.16.840.1.113883.2.4.3.11.60.20.77.2.3.22094"/>
               <reden_van_voorschrijven conceptId="2.16.840.1.113883.2.4.3.11.60.20.77.2.3.23133">
                  <probleem conceptId="2.16.840.1.113883.2.4.3.11.60.20.77.2.3.23134">
                     <probleem_naam code="R97"
                                    codeSystem="2.16.840.1.113883.2.4.4.31.1"
                                    codeSystemName="ICPC-1-NL"
                                    displayName="Hooikoorts/allergische rhinitis"
                                    conceptId="2.16.840.1.113883.2.4.3.11.60.20.77.2.3.23136"/>
                  </probleem>
               </reden_van_voorschrijven>
               <afgesproken_geneesmiddel conceptId="2.16.840.1.113883.2.4.3.11.60.20.77.2.3.19925">
                  <product conceptId="2.16.840.1.113883.2.4.3.11.60.20.77.2.3.22603">
                     <product_code code="59021"
                                   codeSystem="2.16.840.1.113883.2.4.4.10"
                                   codeSystemName="PRK"
                                   displayName="DESLORATADINE TABLET 5MG"
                                   conceptId="2.16.840.1.113883.2.4.3.11.60.20.77.2.3.22604"/>
                     <product_code code="113026"
                                   codeSystem="2.16.840.1.113883.2.4.4.1"
                                   codeSystemName="GPK"
                                   displayName="DESLORATADINE TABLET 5MG"
                                   conceptId="2.16.840.1.113883.2.4.3.11.60.20.77.2.3.22604"/>
                  </product>
               </afgesproken_geneesmiddel>
               <gebruiksinstructie conceptId="2.16.840.1.113883.2.4.3.11.60.20.77.2.3.23240">
                  <omschrijving value="1 keer per dag 1 tablet"
                                conceptId="2.16.840.1.113883.2.4.3.11.60.20.77.2.3.23241"/>
                  <toedieningsweg code="9"
                                  codeSystem="2.16.840.1.113883.2.4.4.9"
                                  displayName="ORAAL"
                                  conceptId="2.16.840.1.113883.2.4.3.11.60.20.77.2.3.23242"/>
                  <doseerinstructie conceptId="2.16.840.1.113883.2.4.3.11.60.20.77.2.3.23245">
                     <volgnummer value="1" conceptId="2.16.840.1.113883.2.4.3.11.60.20.77.2.3.23246"/>
                     <doseerduur value="88"
                                 unit="dag"
                                 conceptId="2.16.840.1.113883.2.4.3.11.60.20.77.2.3.23247"/>
                     <dosering conceptId="2.16.840.1.113883.2.4.3.11.60.20.77.2.3.23248">
                        <keerdosis conceptId="2.16.840.1.113883.2.4.3.11.60.20.77.2.3.23249">
                           <aantal conceptId="2.16.840.1.113883.2.4.3.11.60.20.77.2.3.23250">
                              <vaste_waarde value="1" conceptId="2.16.840.1.113883.2.4.3.11.60.20.77.2.3.23252"/>
                           </aantal>
                           <eenheid code="245"
                                    codeSystem="2.16.840.1.113883.2.4.4.1.900.2"
                                    displayName="STUK"
                                    conceptId="2.16.840.1.113883.2.4.3.11.60.20.77.2.3.23254"/>
                        </keerdosis>
                        <toedieningsschema conceptId="2.16.840.1.113883.2.4.3.11.60.20.77.2.3.23256">
                           <interval value="1"
                                     unit="dag"
                                     conceptId="2.16.840.1.113883.2.4.3.11.60.20.77.2.3.23263"/>
                        </toedieningsschema>
                     </dosering>
                  </doseerinstructie>
               </gebruiksinstructie>
               <kopie_indicator value="false" conceptId="2.16.840.1.113883.2.4.3.11.60.20.77.2.3.23411"/>
            </medicatieafspraak>
         </medicamenteuze_behandeling>
         <medicamenteuze_behandeling conceptId="2.16.840.1.113883.2.4.3.11.60.20.77.2.3.22092">
            <identificatie value="OH-MBH-1551446587591-100008368"
                           root="2.16.840.1.113883.2.4.6.6.90000258.1.100008368"
                           conceptId="2.16.840.1.113883.2.4.3.11.60.20.77.2.3.22093"/>
            <medicatieafspraak conceptId="2.16.840.1.113883.2.4.3.11.60.20.77.2.3.9580">
               <gebruiksperiode_start value="2019-02-08T00:00:00" conceptId="1.2.3.4.5.12345.9580.1"/>
               <gebruiksperiode_eind value="2019-05-08T23:59:59" conceptId="1.2.3.4.5.12345.9580.2"/>
               <identificatie value="15001"
                              root="2.16.840.1.113883.2.4.6.6.90000258.4.4"
                              conceptId="2.16.840.1.113883.2.4.3.11.60.20.77.2.3.19758"/>
               <afspraakdatum value="2019-02-08"
                              conceptId="2.16.840.1.113883.2.4.3.11.60.20.77.2.3.19757"/>
               <relaties_ketenzorg conceptId="2.16.840.1.113883.2.4.3.11.60.20.77.2.3.24024">
                  <identificatie_contactmoment value="996628"
                                               root="2.16.840.1.113883.2.4.6.6.90000258.4.1"
                                               conceptId="2.16.840.1.113883.2.4.3.11.60.20.77.2.3.24026"/>
               </relaties_ketenzorg>
               <voorschrijver conceptId="2.16.840.1.113883.2.4.3.11.60.20.77.2.3.1030">
                  <zorgverlener conceptId="2.16.840.1.113883.2.4.3.11.60.20.77.2.3.19835">
                     <zorgverlener_identificatienummer value="900013866"
                                                       root="2.16.528.1.1007.3.1"
                                                       conceptId="2.16.840.1.113883.2.4.3.11.60.20.77.2.3.19836"/>
                     <naamgegevens conceptId="2.16.840.1.113883.2.4.3.11.60.20.77.2.3.19837">
                        <naamgegevens conceptId="2.16.840.1.113883.2.4.3.11.60.20.77.2.3.19838">
                           <naamgebruik code="UNK"
                                        codeSystem="2.16.840.1.113883.5.1008"
                                        displayName="Unknown"
                                        conceptId="2.16.840.1.113883.2.4.3.11.60.20.77.2.3.19842"/>
                           <geslachtsnaam conceptId="2.16.840.1.113883.2.4.3.11.60.20.77.2.3.19843">
                              <achternaam value="Huisarts 1"
                                          conceptId="2.16.840.1.113883.2.4.3.11.60.20.77.2.3.19845"/>
                           </geslachtsnaam>
                        </naamgegevens>
                     </naamgegevens>
                     <specialisme code="01.015"
                                  codeSystem="2.16.840.1.113883.2.4.15.111"
                                  displayName="Huisarts"
                                  conceptId="2.16.840.1.113883.2.4.3.11.60.20.77.2.3.19849"/>
                     <zorgaanbieder conceptId="2.16.840.1.113883.2.4.3.11.60.20.77.2.3.19871">
                        <zorgaanbieder_identificatienummer value="90000381"
                                                           root="2.16.528.1.1007.3.3"
                                                           conceptId="2.16.840.1.113883.2.4.3.11.60.20.77.2.3.19873"/>
                        <organisatie_naam value="Tést Zorginstelling 04"
                                          conceptId="2.16.840.1.113883.2.4.3.11.60.20.77.2.3.19874"/>
                        <adresgegevens>
                           <straat value="Valkendael 45"/>
                           <postcode value="6245 HK"/>
                           <woonplaats value="Maastricht"/>
                           <land value="Nederland"/>
                           <adres_soort code="WP"
                                        codeSystem="2.16.840.1.113883.5.1119"
                                        displayName="Werkadres"/>
                        </adresgegevens>
                     </zorgaanbieder>
                  </zorgverlener>
               </voorschrijver>
               <reden_wijzigen_of_staken code="OTH"
                                         codeSystem="2.16.840.1.113883.5.1008"
                                         displayName="overig"
                                         originalText="Volgens afspraak"
                                         conceptId="2.16.840.1.113883.2.4.3.11.60.20.77.2.3.22094"/>
               <reden_van_voorschrijven conceptId="2.16.840.1.113883.2.4.3.11.60.20.77.2.3.23133">
                  <probleem conceptId="2.16.840.1.113883.2.4.3.11.60.20.77.2.3.23134">
                     <probleem_naam code="K78"
                                    codeSystem="2.16.840.1.113883.2.4.4.31.1"
                                    codeSystemName="ICPC-1-NL"
                                    displayName="Boezemfibrilleren/-fladderen"
                                    conceptId="2.16.840.1.113883.2.4.3.11.60.20.77.2.3.23136"/>
                  </probleem>
               </reden_van_voorschrijven>
               <afgesproken_geneesmiddel conceptId="2.16.840.1.113883.2.4.3.11.60.20.77.2.3.19925">
                  <product conceptId="2.16.840.1.113883.2.4.3.11.60.20.77.2.3.22603">
                     <product_code code="52191"
                                   codeSystem="2.16.840.1.113883.2.4.4.10"
                                   codeSystemName="PRK"
                                   displayName="CARBASALAATCALCIUM BRUISTABLET 100MG"
                                   conceptId="2.16.840.1.113883.2.4.3.11.60.20.77.2.3.22604"/>
                     <product_code code="106526"
                                   codeSystem="2.16.840.1.113883.2.4.4.1"
                                   codeSystemName="GPK"
                                   displayName="CARBASALAATCALCIUM BRUISTABLET 100MG"
                                   conceptId="2.16.840.1.113883.2.4.3.11.60.20.77.2.3.22604"/>
                  </product>
               </afgesproken_geneesmiddel>
               <gebruiksinstructie conceptId="2.16.840.1.113883.2.4.3.11.60.20.77.2.3.23240">
                  <omschrijving value="1 keer per dag 1 tablet"
                                conceptId="2.16.840.1.113883.2.4.3.11.60.20.77.2.3.23241"/>
                  <toedieningsweg code="9"
                                  codeSystem="2.16.840.1.113883.2.4.4.9"
                                  displayName="ORAAL"
                                  conceptId="2.16.840.1.113883.2.4.3.11.60.20.77.2.3.23242"/>
                  <doseerinstructie conceptId="2.16.840.1.113883.2.4.3.11.60.20.77.2.3.23245">
                     <volgnummer value="1" conceptId="2.16.840.1.113883.2.4.3.11.60.20.77.2.3.23246"/>
                     <doseerduur value="88"
                                 unit="dag"
                                 conceptId="2.16.840.1.113883.2.4.3.11.60.20.77.2.3.23247"/>
                     <dosering conceptId="2.16.840.1.113883.2.4.3.11.60.20.77.2.3.23248">
                        <keerdosis conceptId="2.16.840.1.113883.2.4.3.11.60.20.77.2.3.23249">
                           <aantal conceptId="2.16.840.1.113883.2.4.3.11.60.20.77.2.3.23250">
                              <vaste_waarde value="1" conceptId="2.16.840.1.113883.2.4.3.11.60.20.77.2.3.23252"/>
                           </aantal>
                           <eenheid code="245"
                                    codeSystem="2.16.840.1.113883.2.4.4.1.900.2"
                                    displayName="STUK"
                                    conceptId="2.16.840.1.113883.2.4.3.11.60.20.77.2.3.23254"/>
                        </keerdosis>
                        <toedieningsschema conceptId="2.16.840.1.113883.2.4.3.11.60.20.77.2.3.23256">
                           <interval value="1"
                                     unit="dag"
                                     conceptId="2.16.840.1.113883.2.4.3.11.60.20.77.2.3.23263"/>
                        </toedieningsschema>
                     </dosering>
                  </doseerinstructie>
               </gebruiksinstructie>
               <kopie_indicator value="false" conceptId="2.16.840.1.113883.2.4.3.11.60.20.77.2.3.23411"/>
            </medicatieafspraak>
         </medicamenteuze_behandeling>
      </beschikbaarstellen_medicatieafspraken>
   </data>
</adaxml>
