<MedicationRequest xmlns="http://hl7.org/fhir">
   <id value="MBH-313-2-MA-2"/>
   <meta>
      <profile value="http://nictiz.nl/fhir/StructureDefinition/zib-MedicationAgreement"/>
   </meta>
   <text>
      <status value="extensions"/>
      <div xmlns="http://www.w3.org/1999/xhtml">
         <table>
            <caption>Medicatieafspraak. Subject: J. XXX_Cnossen. Id: MBH_313_2_MA_2 (urn:oid:2.16.840.1.113883.2.4.3.11.999.77.16076005.1), Categorie: <span title="Prescription (procedure) (16076005 - SNOMED CT)">Prescription (procedure)</span>, <span style="display: block;">Intentie: aanvraag</span>
               <span style="display: block;">Aangevraagd door: John de Vries || Huisartsen, niet nader gespecificeerd || Huisartsenpraktijk Pulver &amp; Partners</span>
            </caption>
            <tbody>
               <tr>
                  <th colspan="2">Medicatie is gestopt: <span title="Definitief (2 - 2.16.840.1.113883.2.4.3.11.60.20.77.5.2.1)">Definitief</span>
                  </th>
               </tr>
               <tr>
                  <th>Medicamenteuze behandel-id</th>
                  <td>MBH_313_2 (urn:oid:2.16.840.1.113883.2.4.3.11.999.77.1.1)</td>
               </tr>
               <tr>
                  <th>Medicatie</th>
                  <td>Timolol/Latanoprost oogdr 5mg/50ug/ml fl 2,5ml</td>
               </tr>
               <tr>
                  <th>Gemaakt</th>
                  <td>17:54:00, 2 september 2017</td>
               </tr>
               <tr>
                  <th>Reden</th>
                  <td>
                     <span title="Toedieningsweg voldoet niet (8 - 2.16.840.1.113883.2.4.3.11.60.20.77.5.2.2)">Toedieningsweg voldoet niet</span>
                  </td>
               </tr>
               <tr>
                  <th>Gebruiksduur</th>
                  <td>21 april 2017 00:00:00 - 2 september 2017 17:00:00</td>
               </tr>
               <tr>
                  <th>Doseerinstructie</th>
                  <td>
                     <div>Volgnummer: 1</div>
                     <div>Tekst: Vanaf 21 apr 2017 tot en met 2 sep 2017 17:00, 1x per dag 1 druppel, in beide ogen</div>
                     <div>Instructie: <span title="in beide ogen (1026 - nhg-tabel-25-gebruiksvoorschrift#aanvullend-numeriek)">in beide ogen</span>
                     </div>
                     <div>Timing: <div>eenmalig per dag</div>
                     </div>
                     <div>Toedieningsweg: <span title="oculair (7 - G-Standaard thesaurus subtabel 0007)">oculair</span>
                     </div>
                     <div>Dosering: 1 druppel</div>
                  </td>
               </tr>
            </tbody>
         </table>
      </div>
   </text>
   <extension url="http://nictiz.nl/fhir/StructureDefinition/zib-Medication-PeriodOfUse">
      <valuePeriod>
         <start value="2017-04-21T00:00:00+02:00"/>
         <end value="2017-09-02T17:00:00+02:00"/>
      </valuePeriod>
   </extension>
   <extension url="http://nictiz.nl/fhir/StructureDefinition/zib-Medication-MedicationTreatment">
      <valueIdentifier>
         <system value="urn:oid:2.16.840.1.113883.2.4.3.11.999.77.1.1"/>
         <value value="MBH_313_2"/>
      </valueIdentifier>
   </extension>
   <modifierExtension url="http://nictiz.nl/fhir/StructureDefinition/zib-Medication-StopType">
      <valueCodeableConcept>
         <coding>
            <system value="urn:oid:2.16.840.1.113883.2.4.3.11.60.20.77.5.2.1"/>
            <code value="2"/>
            <display value="Definitief"/>
         </coding>
      </valueCodeableConcept>
   </modifierExtension>
   <identifier>
      <system value="urn:oid:2.16.840.1.113883.2.4.3.11.999.77.16076005.1"/>
      <value value="MBH_313_2_MA_2"/>
   </identifier>
   <intent value="order"/>
   <category>
      <coding>
         <system value="http://snomed.info/sct"/>
         <code value="16076005"/>
         <display value="Prescription (procedure)"/>
      </coding>
      <text value="Medicatieafspraak"/>
   </category>
   <medicationReference>
      <reference value="Medication/60526-2-16-840-1-113883-2-4-4-10"/>
      <display value="Timolol/Latanoprost oogdr 5mg/50ug/ml fl 2,5ml"/>
   </medicationReference>
   <subject>
      <reference value="Patient/XXX-CNOSSEN"/>
      <display value="J. XXX_Cnossen"/>
   </subject>
   <authoredOn value="2017-09-02T17:54:00+02:00"/>
   <requester>
      <agent>
         <extension url="http://nictiz.nl/fhir/StructureDefinition/practitionerrole-reference">
            <valueReference>
               <reference value="PractitionerRole/010000001111"/>
               <display value="John de Vries || Huisartsen, niet nader gespecificeerd || Huisartsenpraktijk Pulver &amp; Partners"/>
            </valueReference>
         </extension>
         <reference value="Practitioner/d6750424-50da-11eb-1835-020000000000"/>
         <display value="John de Vries"/>
      </agent>
   </requester>
   <reasonCode>
      <coding>
         <system value="urn:oid:2.16.840.1.113883.2.4.3.11.60.20.77.5.2.2"/>
         <code value="8"/>
         <display value="Toedieningsweg voldoet niet"/>
      </coding>
   </reasonCode>
   <dosageInstruction>
      <sequence value="1"/>
      <text value="Vanaf 21 apr 2017 tot en met 2 sep 2017 17:00, 1x per dag 1 druppel, in beide ogen"/>
      <additionalInstruction>
         <coding>
            <system value="https://referentiemodel.nhg.org/tabellen/nhg-tabel-25-gebruiksvoorschrift#aanvullend-numeriek"/>
            <code value="1026"/>
            <display value="in beide ogen"/>
         </coding>
      </additionalInstruction>
      <timing>
         <repeat>
            <frequency value="1"/>
            <period value="1"/>
            <periodUnit value="d"/>
         </repeat>
      </timing>
      <route>
         <coding>
            <system value="urn:oid:2.16.840.1.113883.2.4.4.9"/>
            <code value="7"/>
            <display value="oculair"/>
         </coding>
      </route>
      <doseQuantity>
         <value value="1"/>
         <unit value="druppel"/>
         <system value="urn:oid:2.16.840.1.113883.2.4.4.1.900.2"/>
         <code value="303"/>
      </doseQuantity>
   </dosageInstruction>
</MedicationRequest>
