{
  "resourceType": "Bundle",
  "id": "736e3155-f655-4906-898f-4e2a7fb67be6",
  "meta": {
    "lastUpdated": "2026-02-05T13:12:09.237+00:00"
  },
  "type": "searchset",
  "total": 1,
  "link": [
    {
      "relation": "self",
      "url": "https://nictiz.proxy.interoplab.eu/uc-nictiz/stu3/fhir/Observation/$lastn?_revinclude\u003dProvenance%3Atarget\u0026code\u003dhttp%3A%2F%2Floinc.org%7C29463-7\u0026patient\u003dPatient%2FGHANIYA-SAIDA-G-S-N--GHAN-NOERMOHAMED-ELIK\u0026patient.identifier\u003dhttp%3A%2F%2Ffhir.nl%2Ffhir%2FNamingSystem%2Fbsn%7C999901497"
    }
  ],
  "entry": [
    {
      "fullUrl": "https://nictiz.proxy.interoplab.eu/uc-nictiz/stu3/fhir/Observation/zib-BodyWeight-msz-e0c74c0f-6b6d-11ec-0000-2",
      "resource": {
        "resourceType": "Observation",
        "id": "zib-BodyWeight-msz-e0c74c0f-6b6d-11ec-0000-2",
        "meta": {
          "versionId": "64",
          "lastUpdated": "2026-02-03T10:01:45.655+00:00",
          "profile": [
            "http://nictiz.nl/fhir/StructureDefinition/zib-BodyWeight"
          ]
        },
        "text": {
          "status": "extensions",
          "div": "\u003cdiv xmlns\u003d\"http://www.w3.org/1999/xhtml\"\u003e\n      \u003ctable\u003e\n        \u003ccaption\u003eObservatie/bepaling. Subject: Ghaniya Saïda G.S.N. Ghan Noermohamed Çelik. Categorie: \u003cspan title\u003d\"Vital Signs (vital-signs - observation-category)\"\u003eVital Signs\u003c/span\u003e, Status: definitief\u003c/caption\u003e\n        \u003ctfoot\u003e\n          \u003ctr\u003e\n            \u003ctd colspan\u003d\"2\"\u003eMeting aan het eind van de dag, na drie maaltijden.\u003c/td\u003e\n          \u003c/tr\u003e\n        \u003c/tfoot\u003e\n        \u003ctbody\u003e\n          \u003ctr\u003e\n            \u003cth\u003eBepalingdatum/tijd\u003c/th\u003e\n            \u003ctd\u003e22:40:00, 22 juni 2008\u003c/td\u003e\n          \u003c/tr\u003e\n          \u003ctr\u003e\n            \u003cth\u003eCode\u003c/th\u003e\n            \u003cth\u003eWaarde\u003c/th\u003e\n          \u003c/tr\u003e\n          \u003ctr\u003e\n            \u003ctd\u003e\n              \u003cspan title\u003d\"Lichaamsgewicht [massa] in ^patiënt (29463-7 - LOINC)\"\u003eLichaamsgewicht [massa] in ^patiënt\u003c/span\u003e\n            \u003c/td\u003e\n            \u003ctd\u003e92.0 kg\u003c/td\u003e\n          \u003c/tr\u003e\n          \u003ctr\u003e\n            \u003ctd\u003e\n              \u003cspan title\u003d\"Clothing worn during measure (8352-7 - LOINC)\"\u003eClothing worn during measure\u003c/span\u003e\n            \u003c/td\u003e\n            \u003ctd\u003e\n              \u003cspan title\u003d\"Volledig gekleed, inclusief schoenen (FULL - 2.16.840.1.113883.2.4.3.11.60.40.4.8.1)\"\u003eVolledig gekleed, inclusief schoenen\u003c/span\u003e\n            \u003c/td\u003e\n          \u003c/tr\u003e\n        \u003c/tbody\u003e\n      \u003c/table\u003e\n    \u003c/div\u003e"
        },
        "status": "final",
        "category": [
          {
            "coding": [
              {
                "system": "http://hl7.org/fhir/observation-category",
                "code": "vital-signs",
                "display": "Vital Signs"
              }
            ]
          }
        ],
        "code": {
          "coding": [
            {
              "system": "http://loinc.org",
              "code": "29463-7",
              "display": "Lichaamsgewicht [massa] in ^patiënt"
            }
          ]
        },
        "subject": {
          "reference": "Patient/GHANIYA-SAIDA-G-S-N--GHAN-NOERMOHAMED-ELIK",
          "display": "Ghaniya Saïda G.S.N. Ghan Noermohamed Çelik"
        },
        "effectiveDateTime": "2008-06-22T22:40:00+02:00",
        "valueQuantity": {
          "value": 92.0,
          "unit": "kg",
          "system": "http://unitsofmeasure.org",
          "code": "kg"
        },
        "comment": "Meting aan het eind van de dag, na drie maaltijden.",
        "component": [
          {
            "code": {
              "coding": [
                {
                  "system": "http://loinc.org",
                  "code": "8352-7",
                  "display": "Clothing worn during measure"
                }
              ]
            },
            "valueCodeableConcept": {
              "coding": [
                {
                  "system": "urn:oid:2.16.840.1.113883.2.4.3.11.60.40.4.8.1",
                  "code": "FULL",
                  "display": "Volledig gekleed, inclusief schoenen"
                }
              ]
            }
          }
        ]
      },
      "search": {
        "mode": "match"
      }
    }
  ]
}