<adaxml>
    <meta status="new" created-by="camielreijnders" last-update-by="camielreijnders" creation-date="2019-11-18T17:19:32.992+01:00" last-update-date="2019-11-26T09:44:16.772+01:00"/>
    <data>
        <beschikbaarstellen_allergie_intolerantie app="cio" shortName="beschikbaarstellen_allergie_intolerantie" formName="beschikbaarstellen_allergie_intolerantie" transactionRef="2.16.840.1.113883.2.4.3.11.60.26.4.9" transactionEffectiveDate="2019-11-05T13:07:08" versionDate="" prefix="cio-" language="nl-NL" title="1.1" desc="&lt;div&gt;Alle AllergieIntolerantie gegevens van een persoon. Ook geschikt voor scenario 1.2 (met filter mogelijkheid op AllergieCategorie) en 1.3 (met filter mogelijkheid op AllergieStatus).&lt;/div&gt;" id="bs-aig-1-1">
            <patient conceptId="2.16.840.1.113883.2.4.3.11.60.26.2.98" id="AI_Patient_01">
                <naamgegevens conceptId="2.16.840.1.113883.2.4.3.11.60.26.2.100">
                    <voornamen value="Kendrick" conceptId="2.16.840.1.113883.2.4.3.11.60.26.2.111"/>
                    <initialen value="K." conceptId="2.16.840.1.113883.2.4.3.11.60.26.2.112"/>
                    <roepnaam value="Ken" conceptId="2.16.840.1.113883.2.4.3.11.60.26.2.113"/>
                    <naamgebruik conceptId="2.16.840.1.113883.2.4.3.11.60.26.2.114" value="1" code="NL1" codeSystem="2.16.840.1.113883.2.4.3.11.60.101.5.4" displayName="Eigen geslachtsnaam"/>
                    <geslachtsnaam conceptId="2.16.840.1.113883.2.4.3.11.60.26.2.115">
                        <achternaam value="YYY_Yong20" conceptId="2.16.840.1.113883.2.4.3.11.60.26.2.117"/>
                    </geslachtsnaam>
                </naamgegevens>
                <adresgegevens conceptId="2.16.840.1.113883.2.4.3.11.60.26.2.102">
                    <straat value="Knolweg" conceptId="2.16.840.1.113883.2.4.3.11.60.26.2.121"/>
                    <huisnummer value="1003" conceptId="2.16.840.1.113883.2.4.3.11.60.26.2.122"/>
                    <huisnummerletter value="a" conceptId="2.16.840.1.113883.2.4.3.11.60.26.2.123"/>
                    <postcode value="9999 ZA" conceptId="2.16.840.1.113883.2.4.3.11.60.26.2.126"/>
                    <woonplaats value="Stitswerd" conceptId="2.16.840.1.113883.2.4.3.11.60.26.2.127"/>
                    <land code="6030" codeSystem="2.16.840.1.113883.2.4.4.16.34" conceptId="2.16.840.1.113883.2.4.3.11.60.26.2.129" displayName="Nederland"/>
                    <adres_soort conceptId="2.16.840.1.113883.2.4.3.11.60.26.2.131" value="3" code="PHYS" codeSystem="2.16.840.1.113883.5.1119" displayName="Woon-/verblijfadres"/>
                </adresgegevens>
                <contactgegevens conceptId="2.16.840.1.113883.2.4.3.11.60.26.2.104">
                    <telefoonnummers conceptId="2.16.840.1.113883.2.4.3.11.60.26.2.132">
                        <telefoonnummer value="06-12345678" conceptId="2.16.840.1.113883.2.4.3.11.60.26.2.133"/>
                        <telecom_type conceptId="2.16.840.1.113883.2.4.3.11.60.26.2.134" value="3" code="MC" codeSystem="2.16.840.1.113883.5.1119" displayName="Mobiel telefoonnummer"/>
                        <nummer_soort conceptId="2.16.840.1.113883.2.4.3.11.60.26.2.135" value="2" code="TMP" codeSystem="2.16.840.1.113883.5.1119" displayName="Tijdelijk telefoonnummer"/>
                    </telefoonnummers>
                    <email_adressen conceptId="2.16.840.1.113883.2.4.3.11.60.26.2.136">
                        <email_adres value="XXX_Yong@123mail.com" conceptId="2.16.840.1.113883.2.4.3.11.60.26.2.137"/>
                        <email_soort conceptId="2.16.840.1.113883.2.4.3.11.60.26.2.138" value="1" code="HP" codeSystem="2.16.840.1.113883.5.1119" displayName="Privé e-mailadres"/>
                    </email_adressen>
                </contactgegevens>
                <identificatienummer value="999988402" conceptId="2.16.840.1.113883.2.4.3.11.60.26.2.105" root="2.16.840.1.113883.2.4.6.3"/>
                <geboortedatum conceptId="2.16.840.1.113883.2.4.3.11.60.26.2.106" value="1964-08-07" datatype="datetime"/>
                <geslacht conceptId="2.16.840.1.113883.2.4.3.11.60.26.2.107" value="2" code="M" codeSystem="2.16.840.1.113883.5.1" displayName="Man"/>
            </patient>
            <allergie_intolerantie conceptId="2.16.840.1.113883.2.4.3.11.60.26.2.1">
                <zibroot conceptId="2.16.840.1.113883.2.4.3.11.60.26.2.54">
                    <identificatienummer value="AI_01_01" root="2.16.840.1.113883.2.4.3.11.999.26.1.1" conceptId="2.16.840.1.113883.2.4.3.11.60.26.2.55"/>
                    <informatiebron conceptId="2.16.840.1.113883.2.4.3.11.60.26.2.56">
                        <zorgverlener conceptId="2.16.840.1.113883.2.4.3.11.60.26.2.59">
                            <zorgverlener value="AI_Zorgverlener_03" datatype="reference" conceptId="2.16.840.1.113883.2.4.3.11.60.26.2.60"/>
                        </zorgverlener>
                    </informatiebron>
                    <auteur conceptId="2.16.840.1.113883.2.4.3.11.60.26.2.63">
                        <zorgverlener_als_auteur conceptId="2.16.840.1.113883.2.4.3.11.60.26.2.66">
                            <zorgverlener value="AI_Zorgverlener_03" datatype="reference" conceptId="2.16.840.1.113883.2.4.3.11.60.26.2.67"/>
                        </zorgverlener_als_auteur>
                    </auteur>
                    <onderwerp conceptId="2.16.840.1.113883.2.4.3.11.60.26.2.70">
                        <patient conceptId="2.16.840.1.113883.2.4.3.11.60.26.2.71">
                            <patient value="AI_Patient_01" datatype="reference" conceptId="2.16.840.1.113883.2.4.3.11.60.26.2.72"/>
                        </patient>
                    </onderwerp>
                </zibroot>
                <veroorzakende_stof code="1112821" codeSystem="2.16.840.1.113883.2.4.4.7" conceptId="2.16.840.1.113883.2.4.3.11.60.26.2.2" displayName="PREDNISOLON CAPSULE 65MG FNA MR"/>
                <allergie_categorie conceptId="2.16.840.1.113883.2.4.3.11.60.26.2.3" value="2" code="419511003" codeSystem="2.16.840.1.113883.6.96" displayName="Medicijn"/>
                <allergie_status conceptId="2.16.840.1.113883.2.4.3.11.60.26.2.4" value="1" code="active" codeSystem="2.16.840.1.113883.5.14" displayName="Actief"/>
                <begin_datum_tijd value="T-50D" datatype="datetime" conceptId="2.16.840.1.113883.2.4.3.11.60.26.2.5"/>
                <mate_van_kritiek_zijn conceptId="2.16.840.1.113883.2.4.3.11.60.26.2.6" value="3" code="24484000" codeSystem="2.16.840.1.113883.6.96" displayName="Ernstig"/>
                <laatste_reactie_datum_tijd value="T-50D{17:45:00}" datatype="datetime" conceptId="2.16.840.1.113883.2.4.3.11.60.26.2.7"/>
                <toelichting value="Geldt alleen voor dit merk." conceptId="2.16.840.1.113883.2.4.3.11.60.26.2.8"/>
                <reactie conceptId="2.16.840.1.113883.2.4.3.11.60.26.2.9">
                    <symptoom conceptId="2.16.840.1.113883.2.4.3.11.60.26.2.10" value="11" code="23067006" codeSystem="2.16.840.1.113883.6.96" displayName="Toxische epidermale necrolyse"/>
                    <specifieke_stof code="4170" codeSystem="2.16.840.1.113883.2.4.4.1.750" displayName="Prednisolon " conceptId="2.16.840.1.113883.2.4.3.11.60.26.2.11"/>
                    <reactie_beschrijving value="Blaren op grote delen van de huid" conceptId="2.16.840.1.113883.2.4.3.11.60.26.2.12"/>
                    <ernst conceptId="2.16.840.1.113883.2.4.3.11.60.26.2.13" value="3" code="24484000" codeSystem="2.16.840.1.113883.6.96" displayName="Ernstig"/>
                    <reactie_tijdstip value="T-50D{17:45:00}" datatype="datetime" conceptId="2.16.840.1.113883.2.4.3.11.60.26.2.15"/>
                </reactie>
            </allergie_intolerantie>
            <allergie_intolerantie conceptId="2.16.840.1.113883.2.4.3.11.60.26.2.1">
                <zibroot conceptId="2.16.840.1.113883.2.4.3.11.60.26.2.54">
                    <identificatienummer value="AI_01_02" root="2.16.840.1.113883.2.4.3.11.999.26.1.1" conceptId="2.16.840.1.113883.2.4.3.11.60.26.2.55"/>
                    <informatiebron conceptId="2.16.840.1.113883.2.4.3.11.60.26.2.56">
                        <zorgverlener conceptId="2.16.840.1.113883.2.4.3.11.60.26.2.59">
                            <zorgverlener value="AI_Zorgverlener_03" datatype="reference" conceptId="2.16.840.1.113883.2.4.3.11.60.26.2.60"/>
                        </zorgverlener>
                    </informatiebron>
                    <auteur conceptId="2.16.840.1.113883.2.4.3.11.60.26.2.63">
                        <zorgverlener_als_auteur conceptId="2.16.840.1.113883.2.4.3.11.60.26.2.66">
                            <zorgverlener value="AI_Zorgverlener_03" datatype="reference" conceptId="2.16.840.1.113883.2.4.3.11.60.26.2.67"/>
                        </zorgverlener_als_auteur>
                    </auteur>
                    <onderwerp conceptId="2.16.840.1.113883.2.4.3.11.60.26.2.70">
                        <patient conceptId="2.16.840.1.113883.2.4.3.11.60.26.2.71">
                            <patient value="AI_Patient_01" datatype="reference" conceptId="2.16.840.1.113883.2.4.3.11.60.26.2.72"/>
                        </patient>
                    </onderwerp>
                </zibroot>
                <veroorzakende_stof code="4170" codeSystem="2.16.840.1.113883.2.4.4.1.750" displayName="Prednisolon" conceptId="2.16.840.1.113883.2.4.3.11.60.26.2.2"/>
                <allergie_categorie conceptId="2.16.840.1.113883.2.4.3.11.60.26.2.3" value="2" code="419511003" codeSystem="2.16.840.1.113883.6.96" displayName="Medicijn"/>
                <allergie_status conceptId="2.16.840.1.113883.2.4.3.11.60.26.2.4" value="1" code="active" codeSystem="2.16.840.1.113883.5.14" displayName="Actief"/>
                <begin_datum_tijd value="T-100D" datatype="datetime" conceptId="2.16.840.1.113883.2.4.3.11.60.26.2.5"/>
                <mate_van_kritiek_zijn conceptId="2.16.840.1.113883.2.4.3.11.60.26.2.6" value="3" code="24484000" codeSystem="2.16.840.1.113883.6.96" displayName="Ernstig"/>
                <laatste_reactie_datum_tijd value="T-100D" datatype="datetime" conceptId="2.16.840.1.113883.2.4.3.11.60.26.2.7"/>
                <reactie conceptId="2.16.840.1.113883.2.4.3.11.60.26.2.9">
                    <symptoom conceptId="2.16.840.1.113883.2.4.3.11.60.26.2.10" value="11" code="23067006" codeSystem="2.16.840.1.113883.6.96" displayName="Toxische epidermale necrolyse"/>
                    <reactie_beschrijving value="Blaren op grote delen van de huid" conceptId="2.16.840.1.113883.2.4.3.11.60.26.2.12"/>
                    <ernst conceptId="2.16.840.1.113883.2.4.3.11.60.26.2.13" value="3" code="24484000" codeSystem="2.16.840.1.113883.6.96" displayName="Ernstig"/>
                    <wijze_van_blootstelling code="445768003" codeSystem="2.16.840.1.113883.6.96" codeSystemName="SNOMED&#160;CT" displayName="via de maag" conceptId="2.16.840.1.113883.2.4.3.11.60.26.2.14"/>
                    <reactie_tijdstip value="T-100D{11:00:00}" datatype="datetime" conceptId="2.16.840.1.113883.2.4.3.11.60.26.2.15"/>
                </reactie>
            </allergie_intolerantie>
            <allergie_intolerantie conceptId="2.16.840.1.113883.2.4.3.11.60.26.2.1">
                <zibroot conceptId="2.16.840.1.113883.2.4.3.11.60.26.2.54">
                    <identificatienummer value="AI_01_03" root="2.16.840.1.113883.2.4.3.11.999.26.1.1" conceptId="2.16.840.1.113883.2.4.3.11.60.26.2.55"/>
                    <informatiebron conceptId="2.16.840.1.113883.2.4.3.11.60.26.2.56">
                        <zorgverlener conceptId="2.16.840.1.113883.2.4.3.11.60.26.2.59">
                            <zorgverlener value="AI_Zorgverlener_03" datatype="reference" conceptId="2.16.840.1.113883.2.4.3.11.60.26.2.60"/>
                        </zorgverlener>
                    </informatiebron>
                    <auteur conceptId="2.16.840.1.113883.2.4.3.11.60.26.2.63">
                        <zorgverlener_als_auteur conceptId="2.16.840.1.113883.2.4.3.11.60.26.2.66">
                            <zorgverlener value="AI_Zorgverlener_03" datatype="reference" conceptId="2.16.840.1.113883.2.4.3.11.60.26.2.67"/>
                        </zorgverlener_als_auteur>
                    </auteur>
                    <onderwerp conceptId="2.16.840.1.113883.2.4.3.11.60.26.2.70">
                        <patient conceptId="2.16.840.1.113883.2.4.3.11.60.26.2.71">
                            <patient value="AI_Patient_01" datatype="reference" conceptId="2.16.840.1.113883.2.4.3.11.60.26.2.72"/>
                        </patient>
                    </onderwerp>
                </zibroot>
                <veroorzakende_stof code="3158" codeSystem="2.16.840.1.113883.2.4.4.1.725" displayName="Prednisolon oraal" conceptId="2.16.840.1.113883.2.4.3.11.60.26.2.2"/>
                <allergie_categorie conceptId="2.16.840.1.113883.2.4.3.11.60.26.2.3" value="2" code="419511003" codeSystem="2.16.840.1.113883.6.96" displayName="Medicijn"/>
                <allergie_status conceptId="2.16.840.1.113883.2.4.3.11.60.26.2.4" value="1" code="active" codeSystem="2.16.840.1.113883.5.14" displayName="Actief"/>
                <begin_datum_tijd value="T-150D" datatype="datetime" conceptId="2.16.840.1.113883.2.4.3.11.60.26.2.5"/>
                <mate_van_kritiek_zijn conceptId="2.16.840.1.113883.2.4.3.11.60.26.2.6" value="3" code="24484000" codeSystem="2.16.840.1.113883.6.96" displayName="Ernstig"/>
                <laatste_reactie_datum_tijd value="T-150D" datatype="datetime" conceptId="2.16.840.1.113883.2.4.3.11.60.26.2.7"/>
                <reactie conceptId="2.16.840.1.113883.2.4.3.11.60.26.2.9">
                    <symptoom conceptId="2.16.840.1.113883.2.4.3.11.60.26.2.10" value="9" code="271807003" codeSystem="2.16.840.1.113883.6.96" displayName="Exantheem"/>
                    <reactie_beschrijving value="Vlekken en bultjes op de huid" conceptId="2.16.840.1.113883.2.4.3.11.60.26.2.12"/>
                    <ernst conceptId="2.16.840.1.113883.2.4.3.11.60.26.2.13" value="3" code="24484000" codeSystem="2.16.840.1.113883.6.96" displayName="Ernstig"/>
                </reactie>
            </allergie_intolerantie>
            <allergie_intolerantie conceptId="2.16.840.1.113883.2.4.3.11.60.26.2.1">
                <zibroot conceptId="2.16.840.1.113883.2.4.3.11.60.26.2.54">
                    <identificatienummer value="AI_01_04" root="2.16.840.1.113883.2.4.3.11.999.26.1.1" conceptId="2.16.840.1.113883.2.4.3.11.60.26.2.55"/>
                    <informatiebron conceptId="2.16.840.1.113883.2.4.3.11.60.26.2.56">
                        <zorgverlener conceptId="2.16.840.1.113883.2.4.3.11.60.26.2.59">
                            <zorgverlener value="AI_Zorgverlener_03" datatype="reference" conceptId="2.16.840.1.113883.2.4.3.11.60.26.2.60"/>
                        </zorgverlener>
                    </informatiebron>
                    <auteur conceptId="2.16.840.1.113883.2.4.3.11.60.26.2.63">
                        <zorgverlener_als_auteur conceptId="2.16.840.1.113883.2.4.3.11.60.26.2.66">
                            <zorgverlener value="AI_Zorgverlener_03" datatype="reference" conceptId="2.16.840.1.113883.2.4.3.11.60.26.2.67"/>
                        </zorgverlener_als_auteur>
                    </auteur>
                    <onderwerp conceptId="2.16.840.1.113883.2.4.3.11.60.26.2.70">
                        <patient conceptId="2.16.840.1.113883.2.4.3.11.60.26.2.71">
                            <patient value="AI_Patient_01" datatype="reference" conceptId="2.16.840.1.113883.2.4.3.11.60.26.2.72"/>
                        </patient>
                    </onderwerp>
                    <datum_tijd value="T-120D" datatype="datetime" conceptId="2.16.840.1.113883.2.4.3.11.60.26.2.75"/>
                </zibroot>
                <veroorzakende_stof code="74" codeSystem="2.16.840.1.113883.2.4.4.1.902.122" displayName="Corticosteroïden groep 1" conceptId="2.16.840.1.113883.2.4.3.11.60.26.2.2"/>
                <allergie_categorie conceptId="2.16.840.1.113883.2.4.3.11.60.26.2.3" value="2" code="419511003" codeSystem="2.16.840.1.113883.6.96" displayName="Medicijn"/>
                <allergie_status conceptId="2.16.840.1.113883.2.4.3.11.60.26.2.4" value="1" code="active" codeSystem="2.16.840.1.113883.5.14" displayName="Actief"/>
                <begin_datum_tijd value="T-200D" datatype="datetime" conceptId="2.16.840.1.113883.2.4.3.11.60.26.2.5"/>
                <mate_van_kritiek_zijn conceptId="2.16.840.1.113883.2.4.3.11.60.26.2.6" value="3" code="24484000" codeSystem="2.16.840.1.113883.6.96" displayName="Ernstig"/>
                <laatste_reactie_datum_tijd value="T-200D{16:30:00}" datatype="datetime" conceptId="2.16.840.1.113883.2.4.3.11.60.26.2.7"/>
                <reactie conceptId="2.16.840.1.113883.2.4.3.11.60.26.2.9">
                    <symptoom conceptId="2.16.840.1.113883.2.4.3.11.60.26.2.10" value="9" code="271807003" codeSystem="2.16.840.1.113883.6.96" displayName="Exantheem"/>
                    <ernst conceptId="2.16.840.1.113883.2.4.3.11.60.26.2.13" value="3" code="24484000" codeSystem="2.16.840.1.113883.6.96" displayName="Ernstig"/>
                </reactie>
            </allergie_intolerantie>
            <allergie_intolerantie conceptId="2.16.840.1.113883.2.4.3.11.60.26.2.1">
                <zibroot conceptId="2.16.840.1.113883.2.4.3.11.60.26.2.54">
                    <identificatienummer value="AI_01_05" root="2.16.840.1.113883.2.4.3.11.999.26.1.1" conceptId="2.16.840.1.113883.2.4.3.11.60.26.2.55"/>
                    <informatiebron conceptId="2.16.840.1.113883.2.4.3.11.60.26.2.56">
                        <betrokkene_als_bron conceptId="2.16.840.1.113883.2.4.3.11.60.26.2.61">
                            <contactpersoon value="AI_Contactpersoon_01" datatype="reference" conceptId="2.16.840.1.113883.2.4.3.11.60.26.2.62"/>
                        </betrokkene_als_bron>
                    </informatiebron>
                    <auteur conceptId="2.16.840.1.113883.2.4.3.11.60.26.2.63">
                        <zorgverlener_als_auteur conceptId="2.16.840.1.113883.2.4.3.11.60.26.2.66">
                            <zorgverlener value="AI_Zorgverlener_01" datatype="reference" conceptId="2.16.840.1.113883.2.4.3.11.60.26.2.67"/>
                        </zorgverlener_als_auteur>
                    </auteur>
                    <onderwerp conceptId="2.16.840.1.113883.2.4.3.11.60.26.2.70">
                        <patient conceptId="2.16.840.1.113883.2.4.3.11.60.26.2.71">
                            <patient value="AI_Patient_01" datatype="reference" conceptId="2.16.840.1.113883.2.4.3.11.60.26.2.72"/>
                        </patient>
                    </onderwerp>
                </zibroot>
                <veroorzakende_stof code="300916003" codeSystem="2.16.840.1.113883.6.96" displayName="Latex" conceptId="2.16.840.1.113883.2.4.3.11.60.26.2.2"/>
                <allergie_categorie conceptId="2.16.840.1.113883.2.4.3.11.60.26.2.3" value="4" code="419199007" codeSystem="2.16.840.1.113883.6.96" displayName="Stof of product"/>
                <allergie_status conceptId="2.16.840.1.113883.2.4.3.11.60.26.2.4" value="1" code="active" codeSystem="2.16.840.1.113883.5.14" displayName="Actief"/>
                <begin_datum_tijd value="T-3500D" datatype="datetime" conceptId="2.16.840.1.113883.2.4.3.11.60.26.2.5"/>
                <mate_van_kritiek_zijn conceptId="2.16.840.1.113883.2.4.3.11.60.26.2.6" value="2" code="6736007" codeSystem="2.16.840.1.113883.6.96" displayName="Matig"/>
                <laatste_reactie_datum_tijd value="T-265D{14:30:00}" datatype="datetime" conceptId="2.16.840.1.113883.2.4.3.11.60.26.2.7"/>
                <toelichting value="Dhr. werkt in de zorg en dient latexvrije handschoenen te dragen." conceptId="2.16.840.1.113883.2.4.3.11.60.26.2.8"/>
                <reactie conceptId="2.16.840.1.113883.2.4.3.11.60.26.2.9">
                    <symptoom conceptId="2.16.840.1.113883.2.4.3.11.60.26.2.10" value="8" code="418363000" codeSystem="2.16.840.1.113883.6.96" displayName="Jeuk"/>
                    <ernst conceptId="2.16.840.1.113883.2.4.3.11.60.26.2.13" value="2" code="6736007" codeSystem="2.16.840.1.113883.6.96" displayName="Matig"/>
                    <reactie_tijdstip value="T-265D{14:30:00}" datatype="datetime" conceptId="2.16.840.1.113883.2.4.3.11.60.26.2.15"/>
                </reactie>
            </allergie_intolerantie>
            <allergie_intolerantie conceptId="2.16.840.1.113883.2.4.3.11.60.26.2.1">
                <zibroot conceptId="2.16.840.1.113883.2.4.3.11.60.26.2.54">
                    <identificatienummer value="AI_01_06" root="2.16.840.1.113883.2.4.3.11.999.26.1.1" conceptId="2.16.840.1.113883.2.4.3.11.60.26.2.55"/>
                    <informatiebron conceptId="2.16.840.1.113883.2.4.3.11.60.26.2.56">
                        <patient_als_bron conceptId="2.16.840.1.113883.2.4.3.11.60.26.2.57">
                            <patient value="AI_Patient_01" datatype="reference" conceptId="2.16.840.1.113883.2.4.3.11.60.26.2.58"/>
                        </patient_als_bron>
                    </informatiebron>
                    <auteur conceptId="2.16.840.1.113883.2.4.3.11.60.26.2.63">
                        <zorgverlener_als_auteur conceptId="2.16.840.1.113883.2.4.3.11.60.26.2.66">
                            <zorgverlener value="AI_Zorgverlener_02" datatype="reference" conceptId="2.16.840.1.113883.2.4.3.11.60.26.2.67"/>
                        </zorgverlener_als_auteur>
                    </auteur>
                    <onderwerp conceptId="2.16.840.1.113883.2.4.3.11.60.26.2.70">
                        <patient conceptId="2.16.840.1.113883.2.4.3.11.60.26.2.71">
                            <patient value="AI_Patient_01" datatype="reference" conceptId="2.16.840.1.113883.2.4.3.11.60.26.2.72"/>
                        </patient>
                    </onderwerp>
                </zibroot>
                <veroorzakende_stof code="91935009" codeSystem="2.16.840.1.113883.6.96" displayName="Pinda" conceptId="2.16.840.1.113883.2.4.3.11.60.26.2.2"/>
                <allergie_categorie conceptId="2.16.840.1.113883.2.4.3.11.60.26.2.3" value="1" code="418471000" codeSystem="2.16.840.1.113883.6.96" displayName="Voeding"/>
                <allergie_status conceptId="2.16.840.1.113883.2.4.3.11.60.26.2.4" value="2" code="completed" codeSystem="2.16.840.1.113883.5.14" displayName="Niet meer aanwezig"/>
                <begin_datum_tijd value="T-5000D" datatype="datetime" conceptId="2.16.840.1.113883.2.4.3.11.60.26.2.5"/>
            </allergie_intolerantie>
            <allergie_intolerantie conceptId="2.16.840.1.113883.2.4.3.11.60.26.2.1">
                <zibroot conceptId="2.16.840.1.113883.2.4.3.11.60.26.2.54">
                    <identificatienummer value="AI_01_07" root="2.16.840.1.113883.2.4.3.11.999.26.1.1" conceptId="2.16.840.1.113883.2.4.3.11.60.26.2.55"/>
                    <informatiebron conceptId="2.16.840.1.113883.2.4.3.11.60.26.2.56">
                        <zorgverlener conceptId="2.16.840.1.113883.2.4.3.11.60.26.2.59">
                            <zorgverlener value="AI_Zorgverlener_01" datatype="reference" conceptId="2.16.840.1.113883.2.4.3.11.60.26.2.60"/>
                        </zorgverlener>
                    </informatiebron>
                    <auteur conceptId="2.16.840.1.113883.2.4.3.11.60.26.2.63">
                        <zorgverlener_als_auteur conceptId="2.16.840.1.113883.2.4.3.11.60.26.2.66">
                            <zorgverlener value="AI_Zorgverlener_01" datatype="reference" conceptId="2.16.840.1.113883.2.4.3.11.60.26.2.67"/>
                        </zorgverlener_als_auteur>
                    </auteur>
                    <onderwerp conceptId="2.16.840.1.113883.2.4.3.11.60.26.2.70">
                        <patient conceptId="2.16.840.1.113883.2.4.3.11.60.26.2.71">
                            <patient value="AI_Patient_01" datatype="reference" conceptId="2.16.840.1.113883.2.4.3.11.60.26.2.72"/>
                        </patient>
                    </onderwerp>
                </zibroot>
                <veroorzakende_stof code="256259004" codeSystem="2.16.840.1.113883.6.96" displayName="Pollen" conceptId="2.16.840.1.113883.2.4.3.11.60.26.2.2"/>
                <allergie_categorie conceptId="2.16.840.1.113883.2.4.3.11.60.26.2.3" value="3" code="426232007" codeSystem="2.16.840.1.113883.6.96" displayName="Omgeving"/>
                <allergie_status conceptId="2.16.840.1.113883.2.4.3.11.60.26.2.4" value="1" code="active" codeSystem="2.16.840.1.113883.5.14" displayName="Actief"/>
                <begin_datum_tijd value="T-500D" datatype="datetime" conceptId="2.16.840.1.113883.2.4.3.11.60.26.2.5"/>
                <mate_van_kritiek_zijn conceptId="2.16.840.1.113883.2.4.3.11.60.26.2.6" value="2" code="6736007" codeSystem="2.16.840.1.113883.6.96" displayName="Matig"/>
                <laatste_reactie_datum_tijd value="T-99D" datatype="datetime" conceptId="2.16.840.1.113883.2.4.3.11.60.26.2.7"/>
                <reactie conceptId="2.16.840.1.113883.2.4.3.11.60.26.2.9">
                    <symptoom conceptId="2.16.840.1.113883.2.4.3.11.60.26.2.10" value="3" code="490008" codeSystem="2.16.840.1.113883.6.96" displayName="Overgevoeligheidsreactie van de bovenste luchtwegen"/>
                    <specifieke_stof code="256277009" codeSystem="2.16.840.1.113883.6.96" displayName="Graspollen" conceptId="2.16.840.1.113883.2.4.3.11.60.26.2.11"/>
                    <reactie_beschrijving value="Veelvuldig niezen" conceptId="2.16.840.1.113883.2.4.3.11.60.26.2.12"/>
                    <ernst conceptId="2.16.840.1.113883.2.4.3.11.60.26.2.13" value="2" code="6736007" codeSystem="2.16.840.1.113883.6.96" displayName="Matig"/>
                </reactie>
            </allergie_intolerantie>
            <zorgverlener conceptId="2.16.840.1.113883.2.4.3.11.60.26.2.139" id="AI_Zorgverlener_01">
                <zorgverlener_identificatienummer value="111111111" root="2.16.528.1.1007.3.1" conceptId="2.16.840.1.113883.2.4.3.11.60.26.2.140"/>
                <naamgegevens conceptId="2.16.840.1.113883.2.4.3.11.60.26.2.142">
                    <initialen value="A.B." conceptId="2.16.840.1.113883.2.4.3.11.60.26.2.257"/>
                    <naamgebruik conceptId="2.16.840.1.113883.2.4.3.11.60.26.2.259" value="1" code="NL1" codeSystem="2.16.840.1.113883.2.4.3.11.60.101.5.4" displayName="Eigen geslachtsnaam"/>
                    <geslachtsnaam conceptId="2.16.840.1.113883.2.4.3.11.60.26.2.260">
                        <achternaam value="Comenius" conceptId="2.16.840.1.113883.2.4.3.11.60.26.2.262"/>
                    </geslachtsnaam>
                    <geslachtsnaam_partner conceptId="2.16.840.1.113883.2.4.3.11.60.26.2.263">
                        <voorvoegsels_partner value="de" conceptId="2.16.840.1.113883.2.4.3.11.60.26.2.264"/>
                        <achternaam_partner value="Vries" conceptId="2.16.840.1.113883.2.4.3.11.60.26.2.265"/>
                    </geslachtsnaam_partner>
                </naamgegevens>
                <specialisme conceptId="2.16.840.1.113883.2.4.3.11.60.26.2.143" value="82" code="0100" codeSystem="2.16.840.1.113883.2.4.6.7" codeSystemName="COD016-VEKT (Vektis Zorgverlenersspecificatie (subberoepsgroep))" codeSystemVersion="2017-12-14T00:00:00" displayName="Huisartsen, niet nader gespecificeerd"/>
                <contactgegevens conceptId="2.16.840.1.113883.2.4.3.11.60.26.2.147">
                    <telefoonnummers conceptId="2.16.840.1.113883.2.4.3.11.60.26.2.191">
                        <telefoonnummer value="+3143321654" conceptId="2.16.840.1.113883.2.4.3.11.60.26.2.192"/>
                        <telecom_type conceptId="2.16.840.1.113883.2.4.3.11.60.26.2.193" value="1" code="LL" codeSystem="2.16.840.1.113883.2.4.3.11.60.40.4.22.1" displayName="Vast telefoonnummer"/>
                        <nummer_soort conceptId="2.16.840.1.113883.2.4.3.11.60.26.2.194" value="3" code="WP" codeSystem="2.16.840.1.113883.5.1119" displayName="Zakelijk telefoonnummer"/>
                    </telefoonnummers>
                    <email_adressen conceptId="2.16.840.1.113883.2.4.3.11.60.26.2.195">
                        <email_adres value="comenius@hpdetest.nl" conceptId="2.16.840.1.113883.2.4.3.11.60.26.2.196"/>
                        <email_soort conceptId="2.16.840.1.113883.2.4.3.11.60.26.2.197" value="2" code="WP" codeSystem="2.16.840.1.113883.5.1119" displayName="Zakelijk e-mailadres"/>
                    </email_adressen>
                </contactgegevens>
                <zorgaanbieder conceptId="2.16.840.1.113883.2.4.3.11.60.26.2.148">
                    <zorgaanbieder value="AI_Zorgaanbieder_01" datatype="reference" conceptId="2.16.840.1.113883.2.4.3.11.60.26.2.149"/>
                </zorgaanbieder>
                <zorgverleners_rol conceptId="2.16.840.1.113883.2.4.3.11.60.26.2.150" value="1" code="RESP" codeSystem="2.16.840.1.113883.5.90" displayName="Hoofdbehandelaar"/>
            </zorgverlener>
            <zorgverlener conceptId="2.16.840.1.113883.2.4.3.11.60.26.2.139" id="AI_Zorgverlener_02">
                <zorgverlener_identificatienummer value="222222222" root="2.16.528.1.1007.3.1" conceptId="2.16.840.1.113883.2.4.3.11.60.26.2.140"/>
                <naamgegevens conceptId="2.16.840.1.113883.2.4.3.11.60.26.2.142">
                    <voornamen value="Ottobert" conceptId="2.16.840.1.113883.2.4.3.11.60.26.2.256"/>
                    <initialen value="O." conceptId="2.16.840.1.113883.2.4.3.11.60.26.2.257"/>
                    <naamgebruik conceptId="2.16.840.1.113883.2.4.3.11.60.26.2.259" value="1" code="NL1" codeSystem="2.16.840.1.113883.2.4.3.11.60.101.5.4" displayName="Eigen geslachtsnaam"/>
                    <geslachtsnaam conceptId="2.16.840.1.113883.2.4.3.11.60.26.2.260">
                        <voorvoegsels conceptId="2.16.840.1.113883.2.4.3.11.60.26.2.261" value="van"/>
                        <achternaam value="Bekhoven" conceptId="2.16.840.1.113883.2.4.3.11.60.26.2.262"/>
                    </geslachtsnaam>
                </naamgegevens>
                <specialisme conceptId="2.16.840.1.113883.2.4.3.11.60.26.2.143" value="82" code="0100" codeSystem="2.16.840.1.113883.2.4.6.7" codeSystemName="COD016-VEKT (Vektis Zorgverlenersspecificatie (subberoepsgroep))" codeSystemVersion="2017-12-14T00:00:00" displayName="Huisartsen, niet nader gespecificeerd"/>
                <adresgegevens conceptId="2.16.840.1.113883.2.4.3.11.60.26.2.145">
                    <straat value="Valkendael" conceptId="2.16.840.1.113883.2.4.3.11.60.26.2.180"/>
                    <huisnummer value="45" conceptId="2.16.840.1.113883.2.4.3.11.60.26.2.181"/>
                    <postcode value="6245 HK" conceptId="2.16.840.1.113883.2.4.3.11.60.26.2.185"/>
                    <woonplaats value="Maastricht" conceptId="2.16.840.1.113883.2.4.3.11.60.26.2.186"/>
                    <land code="6030" codeSystem="2.16.840.1.113883.2.4.4.16.34" conceptId="2.16.840.1.113883.2.4.3.11.60.26.2.188" displayName="Nederland"/>
                    <adres_soort conceptId="2.16.840.1.113883.2.4.3.11.60.26.2.190" value="5" code="WP" codeSystem="2.16.840.1.113883.5.1119" displayName="Werkadres"/>
                </adresgegevens>
                <contactgegevens conceptId="2.16.840.1.113883.2.4.3.11.60.26.2.147">
                    <telefoonnummers conceptId="2.16.840.1.113883.2.4.3.11.60.26.2.191">
                        <telefoonnummer value="06-32165488" conceptId="2.16.840.1.113883.2.4.3.11.60.26.2.192"/>
                        <telecom_type conceptId="2.16.840.1.113883.2.4.3.11.60.26.2.193" value="3" code="MC" codeSystem="2.16.840.1.113883.5.1119" displayName="Mobiel telefoonnummer"/>
                        <nummer_soort conceptId="2.16.840.1.113883.2.4.3.11.60.26.2.194" value="3" code="WP" codeSystem="2.16.840.1.113883.5.1119" displayName="Zakelijk telefoonnummer"/>
                    </telefoonnummers>
                    <email_adressen conceptId="2.16.840.1.113883.2.4.3.11.60.26.2.195">
                        <email_adres value="o.vanbekhoven@testmedischcentrum.nl" conceptId="2.16.840.1.113883.2.4.3.11.60.26.2.196"/>
                        <email_soort conceptId="2.16.840.1.113883.2.4.3.11.60.26.2.197" value="2" code="WP" codeSystem="2.16.840.1.113883.5.1119" displayName="Zakelijk e-mailadres"/>
                    </email_adressen>
                </contactgegevens>
                <zorgverleners_rol conceptId="2.16.840.1.113883.2.4.3.11.60.26.2.150" value="6" code="ATND" codeSystem="2.16.840.1.113883.5.90" displayName="Behandelaar"/>
            </zorgverlener>
            <zorgverlener conceptId="2.16.840.1.113883.2.4.3.11.60.26.2.139" id="AI_Zorgverlener_03">
                <zorgverlener_identificatienummer value="333333333" root="2.16.528.1.1007.3.1" conceptId="2.16.840.1.113883.2.4.3.11.60.26.2.140"/>
                <naamgegevens conceptId="2.16.840.1.113883.2.4.3.11.60.26.2.142">
                    <initialen value="M." conceptId="2.16.840.1.113883.2.4.3.11.60.26.2.257"/>
                    <naamgebruik conceptId="2.16.840.1.113883.2.4.3.11.60.26.2.259" value="1" code="NL1" codeSystem="2.16.840.1.113883.2.4.3.11.60.101.5.4" displayName="Eigen geslachtsnaam"/>
                    <geslachtsnaam conceptId="2.16.840.1.113883.2.4.3.11.60.26.2.260">
                        <achternaam value="Boot" conceptId="2.16.840.1.113883.2.4.3.11.60.26.2.262"/>
                    </geslachtsnaam>
                </naamgegevens>
                <specialisme conceptId="2.16.840.1.113883.2.4.3.11.60.26.2.143" value="4" code="01.002" codeSystem="2.16.840.1.113883.2.4.15.111" codeSystemName="RoleCodeNL - zorgverlenertype (personen)" codeSystemVersion="2018-09-10T00:00:00" displayName="Allergoloog (gesloten register)"/>
                <adresgegevens conceptId="2.16.840.1.113883.2.4.3.11.60.26.2.145">
                    <straat value="Kamerlingh Onnesstraat" conceptId="2.16.840.1.113883.2.4.3.11.60.26.2.180"/>
                    <huisnummer value="2" conceptId="2.16.840.1.113883.2.4.3.11.60.26.2.181"/>
                    <huisnummertoevoeging value="huis" conceptId="2.16.840.1.113883.2.4.3.11.60.26.2.183"/>
                    <postcode value="2999 AZ" conceptId="2.16.840.1.113883.2.4.3.11.60.26.2.185"/>
                    <woonplaats value="Leiderdorp" conceptId="2.16.840.1.113883.2.4.3.11.60.26.2.186"/>
                    <land code="6030" codeSystem="2.16.840.1.113883.2.4.4.16.34" conceptId="2.16.840.1.113883.2.4.3.11.60.26.2.188" displayName="Nederland"/>
                    <adres_soort conceptId="2.16.840.1.113883.2.4.3.11.60.26.2.190" value="5" code="WP" codeSystem="2.16.840.1.113883.5.1119" displayName="Werkadres"/>
                </adresgegevens>
                <contactgegevens conceptId="2.16.840.1.113883.2.4.3.11.60.26.2.147">
                    <telefoonnummers conceptId="2.16.840.1.113883.2.4.3.11.60.26.2.191">
                        <telefoonnummer value="0800-654321" conceptId="2.16.840.1.113883.2.4.3.11.60.26.2.192"/>
                        <telecom_type conceptId="2.16.840.1.113883.2.4.3.11.60.26.2.193" value="1" code="LL" codeSystem="2.16.840.1.113883.2.4.3.11.60.40.4.22.1" displayName="Vast telefoonnummer"/>
                        <nummer_soort conceptId="2.16.840.1.113883.2.4.3.11.60.26.2.194" value="3" code="WP" codeSystem="2.16.840.1.113883.5.1119" displayName="Zakelijk telefoonnummer"/>
                    </telefoonnummers>
                    <email_adressen conceptId="2.16.840.1.113883.2.4.3.11.60.26.2.195">
                        <email_adres value="m.boot@deallergoloog.nl" conceptId="2.16.840.1.113883.2.4.3.11.60.26.2.196"/>
                        <email_soort conceptId="2.16.840.1.113883.2.4.3.11.60.26.2.197" value="2" code="WP" codeSystem="2.16.840.1.113883.5.1119" displayName="Zakelijk e-mailadres"/>
                    </email_adressen>
                </contactgegevens>
                <zorgverleners_rol conceptId="2.16.840.1.113883.2.4.3.11.60.26.2.150" value="6" code="ATND" codeSystem="2.16.840.1.113883.5.90" displayName="Behandelaar"/>
            </zorgverlener>
            <zorgaanbieder conceptId="2.16.840.1.113883.2.4.3.11.60.26.2.205" id="AI_Zorgaanbieder_01">
                <zorgaanbieder_identificatienummer value="01057999" root="2.16.840.1.113883.2.4.6.1" conceptId="2.16.840.1.113883.2.4.3.11.60.26.2.206"/>
                <organisatie_naam value="Huisartsenpraktijk 'de Test'" conceptId="2.16.840.1.113883.2.4.3.11.60.26.2.207"/>
                <contactgegevens conceptId="2.16.840.1.113883.2.4.3.11.60.26.2.211">
                    <telefoonnummers conceptId="2.16.840.1.113883.2.4.3.11.60.26.2.215">
                        <telefoonnummer value="0800-987653" conceptId="2.16.840.1.113883.2.4.3.11.60.26.2.216"/>
                        <telecom_type conceptId="2.16.840.1.113883.2.4.3.11.60.26.2.217" value="1" code="LL" codeSystem="2.16.840.1.113883.2.4.3.11.60.40.4.22.1" displayName="Vast telefoonnummer"/>
                        <nummer_soort conceptId="2.16.840.1.113883.2.4.3.11.60.26.2.218" value="3" code="WP" codeSystem="2.16.840.1.113883.5.1119" displayName="Zakelijk telefoonnummer"/>
                    </telefoonnummers>
                    <email_adressen conceptId="2.16.840.1.113883.2.4.3.11.60.26.2.219">
                        <email_adres value="info@hpdetest.nl" conceptId="2.16.840.1.113883.2.4.3.11.60.26.2.220"/>
                        <email_soort conceptId="2.16.840.1.113883.2.4.3.11.60.26.2.221" value="2" code="WP" codeSystem="2.16.840.1.113883.5.1119" displayName="Zakelijk e-mailadres"/>
                    </email_adressen>
                </contactgegevens>
                <adresgegevens conceptId="2.16.840.1.113883.2.4.3.11.60.26.2.213">
                    <straat value="Dorpstraat" conceptId="2.16.840.1.113883.2.4.3.11.60.26.2.222"/>
                    <huisnummer value="14" conceptId="2.16.840.1.113883.2.4.3.11.60.26.2.223"/>
                    <postcode value="9244 ZZ" conceptId="2.16.840.1.113883.2.4.3.11.60.26.2.227"/>
                    <woonplaats value="Beetsterzwaag" conceptId="2.16.840.1.113883.2.4.3.11.60.26.2.228"/>
                    <land code="6030" codeSystem="2.16.840.1.113883.2.4.4.16.34" displayName="Nederland" conceptId="2.16.840.1.113883.2.4.3.11.60.26.2.230"/>
                    <adres_soort conceptId="2.16.840.1.113883.2.4.3.11.60.26.2.232" value="5" code="WP" codeSystem="2.16.840.1.113883.5.1119" displayName="Werkadres"/>
                </adresgegevens>
                <organisatie_type conceptId="2.16.840.1.113883.2.4.3.11.60.26.2.214" value="12" code="Z3" codeSystem="2.16.840.1.113883.2.4.15.1060" displayName="Huisartspraktijk (zelfstandig of groepspraktijk)"/>
            </zorgaanbieder>
            <contactpersoon conceptId="2.16.840.1.113883.2.4.3.11.60.26.2.161" id="AI_Contactpersoon_01">
                <naamgegevens conceptId="2.16.840.1.113883.2.4.3.11.60.26.2.163">
                    <voornamen value="Abraham" conceptId="2.16.840.1.113883.2.4.3.11.60.26.2.267"/>
                    <initialen value="B.M.H." conceptId="2.16.840.1.113883.2.4.3.11.60.26.2.268"/>
                    <roepnaam value="Bram" conceptId="2.16.840.1.113883.2.4.3.11.60.26.2.269"/>
                    <naamgebruik conceptId="2.16.840.1.113883.2.4.3.11.60.26.2.270" value="1" code="NL1" codeSystem="2.16.840.1.113883.2.4.3.11.60.101.5.4" displayName="Eigen geslachtsnaam"/>
                    <geslachtsnaam conceptId="2.16.840.1.113883.2.4.3.11.60.26.2.271">
                        <achternaam value="Pasveer" conceptId="2.16.840.1.113883.2.4.3.11.60.26.2.273"/>
                    </geslachtsnaam>
                </naamgegevens>
                <contactgegevens conceptId="2.16.840.1.113883.2.4.3.11.60.26.2.157">
                    <telefoonnummers conceptId="2.16.840.1.113883.2.4.3.11.60.26.2.198">
                        <telefoonnummer value="06-12345670" conceptId="2.16.840.1.113883.2.4.3.11.60.26.2.199"/>
                        <telecom_type conceptId="2.16.840.1.113883.2.4.3.11.60.26.2.200" value="3" code="MC" codeSystem="2.16.840.1.113883.5.1119" displayName="Mobiel telefoonnummer"/>
                    </telefoonnummers>
                    <email_adressen conceptId="2.16.840.1.113883.2.4.3.11.60.26.2.202">
                        <email_adres value="brampasveer_123@hotmail.com" conceptId="2.16.840.1.113883.2.4.3.11.60.26.2.203"/>
                        <email_soort conceptId="2.16.840.1.113883.2.4.3.11.60.26.2.204" value="1" code="HP" codeSystem="2.16.840.1.113883.5.1119" displayName="Privé e-mailadres"/>
                    </email_adressen>
                </contactgegevens>
                <adresgegevens conceptId="2.16.840.1.113883.2.4.3.11.60.26.2.167">
                    <straat value="Bolweg" conceptId="2.16.840.1.113883.2.4.3.11.60.26.2.243"/>
                    <huisnummer value="99" conceptId="2.16.840.1.113883.2.4.3.11.60.26.2.244"/>
                    <postcode value="9999 XX" conceptId="2.16.840.1.113883.2.4.3.11.60.26.2.248"/>
                    <woonplaats value="Stitswerd" conceptId="2.16.840.1.113883.2.4.3.11.60.26.2.249"/>
                    <land code="6030" codeSystem="2.16.840.1.113883.2.4.4.16.34" conceptId="2.16.840.1.113883.2.4.3.11.60.26.2.251" displayName="Nederland"/>
                    <adres_soort conceptId="2.16.840.1.113883.2.4.3.11.60.26.2.253" value="3" code="PHYS" codeSystem="2.16.840.1.113883.5.1119" displayName="Woon-/verblijfadres"/>
                </adresgegevens>
                <rol conceptId="2.16.840.1.113883.2.4.3.11.60.26.2.168" value="13" code="20" codeSystem="2.16.840.1.113883.2.4.3.11.22.472" displayName="Vriend(in)/kennis"/>
                <relatie conceptId="2.16.840.1.113883.2.4.3.11.60.26.2.169" originalText="Boezemvriend" value="35" code="OTH" codeSystem="2.16.840.1.113883.5.1008" displayName="Anders"/>
            </contactpersoon>
        </beschikbaarstellen_allergie_intolerantie>
    </data>
</adaxml>